[{"X":-4.4064,"Y":-1.2726,"type":"T"},{"X":-2.5413,"Y":-1.7167,"type":"T"},{"X":-3.7561,"Y":-2.3397,"type":"T"},{"X":-4.2396,"Y":-1.0436,"type":"T"},{"X":-3.3745,"Y":-1.009,"type":"T"},{"X":-2.6627,"Y":-1.617,"type":"T"},{"X":-2.4791,"Y":-2.2697,"type":"T"},{"X":-4.2532,"Y":-1.4056,"type":"T"},{"X":-1.7437,"Y":-2.0114,"type":"T"},{"X":-3.5123,"Y":-0.4994,"type":"T"},{"X":-3.5917,"Y":-1.6944,"type":"T"},{"X":-3.8132,"Y":-1.6304,"type":"T"},{"X":-4.2055,"Y":-1.4817,"type":"T"},{"X":-2.4813,"Y":-1.6699,"type":"T"},{"X":-3.928,"Y":-2.1742,"type":"T"},{"X":-4.4657,"Y":-0.7778,"type":"T"},{"X":-2.8232,"Y":-1.9196,"type":"T"},{"X":-4.3287,"Y":-1.985,"type":"T"},{"X":-3.6065,"Y":-1.7242,"type":"T"},{"X":-1.8038,"Y":-0.7927,"type":"T"},{"X":-3.9296,"Y":-1.9784,"type":"T"},{"X":-3.529,"Y":-1.4782,"type":"T"},{"X":-3.2682,"Y":-2.2994,"type":"T"},{"X":-2.9632,"Y":-1.7336,"type":"T"},{"X":-3.4588,"Y":-1.4018,"type":"T"},{"X":-4.2053,"Y":-1.3684,"type":"T"},{"X":-2.4204,"Y":-1.8824,"type":"T"},{"X":-3.927,"Y":-1.7322,"type":"T"},{"X":-4.0398,"Y":-0.8376,"type":"T"},{"X":-3.7016,"Y":-1.5041,"type":"T"},{"X":-3.9464,"Y":-1.7751,"type":"T"},{"X":-3.8138,"Y":-1.9609,"type":"T"},{"X":-3.4341,"Y":-2.2459,"type":"T"},{"X":-4.0519,"Y":-2.2257,"type":"T"},{"X":-3.4532,"Y":-1.303,"type":"T"},{"X":2.1778,"Y":-1.0651,"type":"T"},{"X":-3.0981,"Y":-2.3814,"type":"T"},{"X":-4.2043,"Y":-1.5506,"type":"T"},{"X":-3.9169,"Y":-2.0615,"type":"T"},{"X":-4.6186,"Y":-2.047,"type":"T"},{"X":-4.1133,"Y":-1.5125,"type":"T"},{"X":-5.0691,"Y":-2.728,"type":"T"},{"X":-4.1379,"Y":-2.617,"type":"T"},{"X":-2.5277,"Y":-1.3794,"type":"T"},{"X":-3.5407,"Y":-1.7414,"type":"T"},{"X":-3.6958,"Y":-1.7576,"type":"T"},{"X":-2.8221,"Y":-1.8707,"type":"T"},{"X":-3.4747,"Y":-2.7692,"type":"T"},{"X":-3.9176,"Y":-1.1231,"type":"T"},{"X":-3.0853,"Y":-1.029,"type":"T"},{"X":-2.6281,"Y":-1.5949,"type":"T"},{"X":-3.8273,"Y":-2.5219,"type":"T"},{"X":-3.5243,"Y":-2.7811,"type":"T"},{"X":-4.2304,"Y":-2.3397,"type":"T"},{"X":-4.0185,"Y":-1.2303,"type":"T"},{"X":-2.5199,"Y":-2.2493,"type":"T"},{"X":-4.7223,"Y":-1.7521,"type":"T"},{"X":-3.8156,"Y":-0.7336,"type":"T"},{"X":-3.9661,"Y":-1.1409,"type":"T"},{"X":-3.3041,"Y":-1.2167,"type":"T"},{"X":-3.3816,"Y":-2.3226,"type":"T"},{"X":-4.1014,"Y":-2.4692,"type":"T"},{"X":-4.0719,"Y":-0.7802,"type":"T"},{"X":-4.3865,"Y":-2.1105,"type":"T"},{"X":-0.5862,"Y":-1.9613,"type":"T"},{"X":-3.1636,"Y":-2.136,"type":"T"},{"X":-4.6501,"Y":-0.9096,"type":"T"},{"X":-3.897,"Y":-2.5669,"type":"T"},{"X":-4.212,"Y":-1.8841,"type":"T"},{"X":-3.8407,"Y":-3.0417,"type":"T"},{"X":-3.8387,"Y":-1.8066,"type":"T"},{"X":-4.4462,"Y":-1.1797,"type":"T"},{"X":-3.5427,"Y":-1.6534,"type":"T"},{"X":-2.5768,"Y":-2.5381,"type":"T"},{"X":-2.9153,"Y":-1.5095,"type":"T"},{"X":-4.665,"Y":-1.2471,"type":"T"},{"X":-4.0106,"Y":-0.9531,"type":"T"},{"X":-3.7361,"Y":-2.3928,"type":"T"},{"X":-4.015,"Y":-2.5144,"type":"T"},{"X":-4.1161,"Y":-2.4726,"type":"T"},{"X":-3.8844,"Y":-1.4586,"type":"T"},{"X":-4.2895,"Y":-2.3574,"type":"T"},{"X":-3.8236,"Y":-0.9611,"type":"T"},{"X":-4.9232,"Y":-1.7816,"type":"T"},{"X":-1.6358,"Y":-1.5589,"type":"T"},{"X":-4.2439,"Y":-1.8761,"type":"T"},{"X":-4.2679,"Y":-1.4469,"type":"T"},{"X":-4.4066,"Y":-1.3559,"type":"T"},{"X":-4.5184,"Y":-0.7075,"type":"T"},{"X":-4.5375,"Y":-1.873,"type":"T"},{"X":-2.4566,"Y":-1.9397,"type":"T"},{"X":-2.0244,"Y":-1.981,"type":"T"},{"X":-3.9937,"Y":-1.9701,"type":"T"},{"X":-3.9513,"Y":-0.834,"type":"T"},{"X":-4.2481,"Y":-1.6281,"type":"T"},{"X":-3.8256,"Y":-1.8825,"type":"T"},{"X":-4.5901,"Y":-1.3812,"type":"T"},{"X":-3.7731,"Y":-0.8458,"type":"T"},{"X":-2.5273,"Y":-2.1542,"type":"T"},{"X":-4.2244,"Y":-2.0955,"type":"T"},{"X":-4.0655,"Y":-1.5983,"type":"T"},{"X":-3.8961,"Y":-1.1787,"type":"T"},{"X":-4.854,"Y":-1.2024,"type":"T"},{"X":-3.8884,"Y":-2.1751,"type":"T"},{"X":-4.3105,"Y":-1.5317,"type":"T"},{"X":-2.7477,"Y":-1.5839,"type":"T"},{"X":-4.3507,"Y":-1.4661,"type":"T"},{"X":-3.9625,"Y":-1.7061,"type":"T"},{"X":-4.4218,"Y":-2.0498,"type":"T"},{"X":-3.501,"Y":-1.6573,"type":"T"},{"X":-2.5252,"Y":-1.5702,"type":"T"},{"X":-4.0121,"Y":-0.8741,"type":"T"},{"X":-4.1335,"Y":-1.9939,"type":"T"},{"X":-3.9192,"Y":-2.3897,"type":"T"},{"X":-3.9671,"Y":-1.659,"type":"T"},{"X":-3.9452,"Y":-2.1725,"type":"T"},{"X":-3.1922,"Y":-1.862,"type":"T"},{"X":-2.6018,"Y":-2.5578,"type":"T"},{"X":-4.0249,"Y":-2.395,"type":"T"},{"X":-3.5506,"Y":-1.9822,"type":"T"},{"X":-4.3759,"Y":-1.1563,"type":"T"},{"X":-4.732,"Y":-1.4877,"type":"T"},{"X":-3.6741,"Y":-0.699,"type":"T"},{"X":-4.3074,"Y":-1.6187,"type":"T"},{"X":-3.9395,"Y":-1.7486,"type":"T"},{"X":-2.6811,"Y":-1.5004,"type":"T"},{"X":-3.6633,"Y":-1.5126,"type":"T"},{"X":-4.0824,"Y":-1.3047,"type":"T"},{"X":-3.5061,"Y":-2.1285,"type":"T"},{"X":-3.5092,"Y":-1.4275,"type":"T"},{"X":-3.4243,"Y":-2.2895,"type":"T"},{"X":-3.8422,"Y":-1.9385,"type":"T"},{"X":-4.1172,"Y":-1.8213,"type":"T"},{"X":-4.1734,"Y":-2.3712,"type":"T"},{"X":2.0645,"Y":-1.1882,"type":"T"},{"X":-3.514,"Y":-2.117,"type":"T"},{"X":-4.031,"Y":-1.8262,"type":"T"},{"X":-2.6308,"Y":-1.8451,"type":"T"},{"X":-3.8855,"Y":-1.6141,"type":"T"},{"X":-4.3124,"Y":-1.8459,"type":"T"},{"X":-4.3865,"Y":-1.4188,"type":"T"},{"X":-4.2568,"Y":-1.5861,"type":"T"},{"X":-3.7783,"Y":-1.6594,"type":"T"},{"X":-4.0695,"Y":-1.1349,"type":"T"},{"X":-3.0142,"Y":-1.7271,"type":"T"},{"X":-3.9119,"Y":-1.9892,"type":"T"},{"X":-4.2278,"Y":-1.5227,"type":"T"},{"X":-2.0956,"Y":-2.1627,"type":"T"},{"X":-3.3389,"Y":-2.1352,"type":"T"},{"X":-3.5103,"Y":-1.6104,"type":"T"},{"X":-4.044,"Y":-2.137,"type":"T"},{"X":-3.8542,"Y":-2.7646,"type":"T"},{"X":-4.0373,"Y":-1.7362,"type":"T"},{"X":-4.2039,"Y":-1.1825,"type":"T"},{"X":-4.0756,"Y":-1.3178,"type":"T"},{"X":-3.9931,"Y":-2.6373,"type":"T"},{"X":-3.9602,"Y":-1.5879,"type":"T"},{"X":-3.8179,"Y":-2.0555,"type":"T"},{"X":-4.52,"Y":-0.9141,"type":"T"},{"X":-3.6782,"Y":-1.5665,"type":"T"},{"X":-2.8628,"Y":-1.9317,"type":"T"},{"X":-3.6546,"Y":-2.1169,"type":"T"},{"X":-3.8903,"Y":-1.1894,"type":"T"},{"X":-1.263,"Y":-1.3113,"type":"T"},{"X":-3.5941,"Y":-1.6534,"type":"T"},{"X":-2.7171,"Y":-1.797,"type":"T"},{"X":-4.0002,"Y":-2.4375,"type":"T"},{"X":-3.5117,"Y":-1.9537,"type":"T"},{"X":-1.7954,"Y":-0.6645,"type":"T"},{"X":-3.8693,"Y":-2.576,"type":"T"},{"X":-4.083,"Y":-1.7969,"type":"T"},{"X":-2.7699,"Y":-2.0195,"type":"T"},{"X":-3.952,"Y":-1.5031,"type":"T"},{"X":-3.7696,"Y":-1.6904,"type":"T"},{"X":-3.5671,"Y":-2.522,"type":"T"},{"X":-4.5443,"Y":-2.3679,"type":"T"},{"X":-3.4355,"Y":-2.3907,"type":"T"},{"X":-2.1798,"Y":-1.4363,"type":"T"},{"X":-2.8809,"Y":-1.8046,"type":"T"},{"X":-3.5607,"Y":-1.5665,"type":"T"},{"X":-4.097,"Y":-1.7993,"type":"T"},{"X":-3.6011,"Y":-2.1266,"type":"T"},{"X":-3.9711,"Y":-0.9644,"type":"T"},{"X":-4.1611,"Y":-0.6488,"type":"T"},{"X":-4.0586,"Y":-2.3678,"type":"T"},{"X":-3.8067,"Y":-2.3309,"type":"T"},{"X":-4.0598,"Y":-0.9076,"type":"T"},{"X":-3.8169,"Y":-2.363,"type":"T"},{"X":-2.7496,"Y":-1.8843,"type":"T"},{"X":-4.3347,"Y":-1.4905,"type":"T"},{"X":-3.8147,"Y":-1.8655,"type":"T"},{"X":-3.4926,"Y":-2.8838,"type":"T"},{"X":-3.6433,"Y":-1.5278,"type":"T"},{"X":-2.4028,"Y":-1.9598,"type":"T"},{"X":-4.3621,"Y":-1.9222,"type":"T"},{"X":-4.0045,"Y":-1.5971,"type":"T"},{"X":-4.3412,"Y":-0.924,"type":"T"},{"X":-4.1068,"Y":-1.025,"type":"T"},{"X":-3.9617,"Y":-0.6249,"type":"T"},{"X":-3.9173,"Y":-2.058,"type":"T"},{"X":-4.1899,"Y":-0.9549,"type":"T"},{"X":-3.7551,"Y":-1.5983,"type":"T"},{"X":-3.3782,"Y":-2.1649,"type":"T"},{"X":-4.2031,"Y":-1.9317,"type":"T"},{"X":-3.4964,"Y":-2.369,"type":"T"},{"X":-4.398,"Y":-1.6603,"type":"T"},{"X":-4.3513,"Y":-1.914,"type":"T"},{"X":-3.6967,"Y":-1.877,"type":"T"},{"X":-4.6289,"Y":-1.9483,"type":"T"},{"X":-2.8574,"Y":-1.4472,"type":"T"},{"X":-3.0962,"Y":-0.7613,"type":"T"},{"X":-2.9923,"Y":-2.1955,"type":"T"},{"X":-3.1029,"Y":-2.0362,"type":"T"},{"X":-2.1883,"Y":-1.5472,"type":"T"},{"X":-3.23,"Y":-3.336,"type":"T"},{"X":-4.4355,"Y":-1.7318,"type":"T"},{"X":-3.932,"Y":-1.9107,"type":"T"},{"X":-3.8435,"Y":-1.708,"type":"T"},{"X":-4.0515,"Y":-1.1868,"type":"T"},{"X":-4.0436,"Y":-2.396,"type":"T"},{"X":-4.5825,"Y":-1.7032,"type":"T"},{"X":-4.1457,"Y":-2.1952,"type":"T"},{"X":-4.0782,"Y":-1.9812,"type":"T"},{"X":-3.4773,"Y":-1.2505,"type":"T"},{"X":-3.9725,"Y":-0.7547,"type":"T"},{"X":-3.5606,"Y":-1.996,"type":"T"},{"X":-4.1415,"Y":-1.8417,"type":"T"},{"X":-3.6913,"Y":-1.7712,"type":"T"},{"X":-2.8248,"Y":-2.5173,"type":"T"},{"X":-3.8558,"Y":-1.0565,"type":"T"},{"X":-2.3555,"Y":-1.6067,"type":"T"},{"X":-3.8791,"Y":-1.5143,"type":"T"},{"X":-4.2462,"Y":-1.7748,"type":"T"},{"X":-3.4968,"Y":-2.7619,"type":"T"},{"X":-4.681,"Y":-1.6422,"type":"T"},{"X":-3.8135,"Y":-2.3728,"type":"T"},{"X":-3.9411,"Y":-1.6455,"type":"T"},{"X":-3.9113,"Y":-1.7851,"type":"T"},{"X":-4.0585,"Y":-1.8317,"type":"T"},{"X":-2.7664,"Y":-1.6976,"type":"T"},{"X":-4.175,"Y":-1.7244,"type":"T"},{"X":-3.4776,"Y":-2.4254,"type":"T"},{"X":-4.4198,"Y":-1.27,"type":"T"},{"X":-3.9676,"Y":-1.9505,"type":"T"},{"X":-4.3483,"Y":-1.679,"type":"T"},{"X":-3.9578,"Y":-2.0577,"type":"T"},{"X":-3.9959,"Y":-1.807,"type":"T"},{"X":-3.9038,"Y":-1.0882,"type":"T"},{"X":-2.9099,"Y":-2.7595,"type":"T"},{"X":-4.6903,"Y":-1.3733,"type":"T"},{"X":-4.2285,"Y":-1.7291,"type":"T"},{"X":-2.4773,"Y":-1.9195,"type":"T"},{"X":-3.9846,"Y":-1.0447,"type":"T"},{"X":-3.3631,"Y":-1.7677,"type":"T"},{"X":-4.3807,"Y":-1.2525,"type":"T"},{"X":-4.1008,"Y":-1.1639,"type":"T"},{"X":-4.0864,"Y":-1.6302,"type":"T"},{"X":-4.2314,"Y":-2.2699,"type":"T"},{"X":-2.7753,"Y":-1.667,"type":"T"},{"X":-3.9635,"Y":-2.3443,"type":"T"},{"X":-4.0512,"Y":-1.6244,"type":"T"},{"X":-3.7694,"Y":-1.2728,"type":"T"},{"X":-5.0837,"Y":-1.897,"type":"T"},{"X":-4.6789,"Y":-1.952,"type":"T"},{"X":-3.6793,"Y":-1.1734,"type":"T"},{"X":-3.6901,"Y":-2.3028,"type":"T"},{"X":-4.0665,"Y":-2.1291,"type":"T"},{"X":-3.7746,"Y":-1.0498,"type":"T"},{"X":-3.8542,"Y":-1.3057,"type":"T"},{"X":-2.5203,"Y":-2.3336,"type":"T"},{"X":-3.7872,"Y":-2.2802,"type":"T"},{"X":-3.5003,"Y":-2.6778,"type":"T"},{"X":-4.0354,"Y":-2.3243,"type":"T"},{"X":-3.9128,"Y":-2.2773,"type":"T"},{"X":-4.426,"Y":-1.3776,"type":"T"},{"X":-3.8044,"Y":-1.243,"type":"T"},{"X":-4.0856,"Y":-2.0997,"type":"T"},{"X":-4.3218,"Y":-1.4603,"type":"T"},{"X":-2.574,"Y":-1.7103,"type":"T"},{"X":-4.1289,"Y":-0.9947,"type":"T"},{"X":-3.8955,"Y":-2.52,"type":"T"},{"X":-4.659,"Y":-2.0915,"type":"T"},{"X":-1.8686,"Y":-2.7552,"type":"T"},{"X":-4.2099,"Y":-2.166,"type":"T"},{"X":-2.4211,"Y":-0.7871,"type":"T"},{"X":-3.8267,"Y":-1.8775,"type":"T"},{"X":-3.8092,"Y":-1.5288,"type":"T"},{"X":-2.9372,"Y":-2.2909,"type":"T"},{"X":-4.3347,"Y":-1.0977,"type":"T"},{"X":-3.0053,"Y":-1.1625,"type":"T"},{"X":0.5285,"Y":-1.8147,"type":"T"},{"X":-2.1507,"Y":-2.2617,"type":"T"},{"X":-3.4444,"Y":-2.0429,"type":"T"},{"X":-4.6187,"Y":-1.5947,"type":"T"},{"X":-3.9039,"Y":-2.8116,"type":"T"},{"X":-3.9991,"Y":-1.3674,"type":"T"},{"X":-4.5019,"Y":-0.5854,"type":"T"},{"X":-5.3086,"Y":-1.4834,"type":"T"},{"X":-2.3456,"Y":-1.4837,"type":"T"},{"X":-4.6292,"Y":-1.5836,"type":"T"},{"X":-4.3701,"Y":-2.2213,"type":"T"},{"X":-2.5409,"Y":-1.744,"type":"T"},{"X":-4.0386,"Y":-0.9764,"type":"T"},{"X":-1.997,"Y":-2.5112,"type":"T"},{"X":-4.3392,"Y":-1.1273,"type":"T"},{"X":-4.1532,"Y":-1.9058,"type":"T"},{"X":-3.564,"Y":-1.5898,"type":"T"},{"X":-4.2926,"Y":-2.5859,"type":"T"},{"X":-3.5804,"Y":-2.0819,"type":"T"},{"X":-3.4839,"Y":-1.6416,"type":"T"},{"X":-3.5408,"Y":-1.7485,"type":"T"},{"X":-3.7217,"Y":-1.6723,"type":"T"},{"X":-4.0174,"Y":-1.8844,"type":"T"},{"X":-4.5895,"Y":-1.028,"type":"T"},{"X":-3.6466,"Y":-1.471,"type":"T"},{"X":-4.288,"Y":-1.5813,"type":"T"},{"X":-4.0621,"Y":-1.7376,"type":"T"},{"X":-4.0364,"Y":-1.0419,"type":"T"},{"X":-3.6732,"Y":-1.3444,"type":"T"},{"X":-5.366,"Y":-2.1199,"type":"T"},{"X":-3.6394,"Y":-1.5624,"type":"T"},{"X":-4.1383,"Y":-1.0395,"type":"T"},{"X":-4.0008,"Y":-1.2462,"type":"T"},{"X":-2.1064,"Y":-2.2321,"type":"T"},{"X":-2.6199,"Y":-1.0566,"type":"T"},{"X":-3.376,"Y":-1.2957,"type":"T"},{"X":-4.5181,"Y":-1.6958,"type":"T"},{"X":-3.3785,"Y":-1.634,"type":"T"},{"X":-3.333,"Y":-1.1779,"type":"T"},{"X":-3.9717,"Y":-2.1956,"type":"T"},{"X":-3.7962,"Y":-2.343,"type":"T"},{"X":-3.7293,"Y":-2.0976,"type":"T"},{"X":-3.135,"Y":-2.1621,"type":"T"},{"X":-4.1481,"Y":-1.3482,"type":"T"},{"X":-3.8253,"Y":-0.8817,"type":"T"},{"X":-4.5945,"Y":-0.4315,"type":"T"},{"X":-3.9391,"Y":-1.7243,"type":"T"},{"X":-4.0089,"Y":-1.7818,"type":"T"},{"X":-4.3697,"Y":-2.1018,"type":"T"},{"X":-3.6027,"Y":-1.4398,"type":"T"},{"X":-3.8442,"Y":-0.8847,"type":"T"},{"X":-4.1226,"Y":-2.0064,"type":"T"},{"X":-4.1602,"Y":-2.1313,"type":"T"},{"X":-4.0294,"Y":-1.2571,"type":"T"},{"X":-3.3388,"Y":-1.5846,"type":"T"},{"X":-3.6837,"Y":-0.7414,"type":"T"},{"X":-3.6914,"Y":-1.5487,"type":"T"},{"X":-4.0169,"Y":-1.9316,"type":"T"},{"X":-4.3303,"Y":-1.7242,"type":"T"},{"X":-3.5491,"Y":-1.5008,"type":"T"},{"X":-5.3581,"Y":-1.8784,"type":"T"},{"X":-4.2928,"Y":-2.0526,"type":"T"},{"X":-3.4239,"Y":-2.1367,"type":"T"},{"X":-2.9233,"Y":-1.9341,"type":"T"},{"X":-3.3829,"Y":-1.8645,"type":"T"},{"X":-4.4735,"Y":-1.8648,"type":"T"},{"X":-3.7099,"Y":-2.1347,"type":"T"},{"X":-3.6131,"Y":-1.9233,"type":"T"},{"X":-1.7413,"Y":-1.1943,"type":"T"},{"X":-4.0404,"Y":-1.9976,"type":"T"},{"X":-4.1185,"Y":-2.6972,"type":"T"},{"X":-4.1685,"Y":-1.9768,"type":"T"},{"X":-3.9027,"Y":-2.2793,"type":"T"},{"X":-3.9496,"Y":-2.36,"type":"T"},{"X":-3.517,"Y":-2.254,"type":"T"},{"X":-3.0383,"Y":-1.7764,"type":"T"},{"X":-2.3377,"Y":-1.8654,"type":"T"},{"X":-4.4195,"Y":-2.1454,"type":"T"},{"X":-4.9831,"Y":-0.7952,"type":"T"},{"X":-2.8045,"Y":-1.6736,"type":"T"},{"X":-3.8045,"Y":-1.1837,"type":"T"},{"X":-4.6116,"Y":-1.6255,"type":"T"},{"X":-4.4655,"Y":-1.8646,"type":"T"},{"X":-3.7365,"Y":-1.9103,"type":"T"},{"X":-3.4289,"Y":-1.1097,"type":"T"},{"X":-3.2277,"Y":-2.6458,"type":"T"},{"X":-3.9867,"Y":-1.9775,"type":"T"},{"X":-4.3562,"Y":-1.4842,"type":"T"},{"X":-4.3516,"Y":-2.021,"type":"T"},{"X":-3.5342,"Y":-0.8525,"type":"T"},{"X":-3.6509,"Y":-1.9309,"type":"T"},{"X":-3.5907,"Y":-1.8462,"type":"T"},{"X":-3.64,"Y":-1.8394,"type":"T"},{"X":-2.282,"Y":-1.7332,"type":"T"},{"X":-2.6242,"Y":-1.5039,"type":"T"},{"X":-3.6735,"Y":-1.6343,"type":"T"},{"X":-3.2173,"Y":-1.053,"type":"T"},{"X":-4.6736,"Y":-1.6754,"type":"T"},{"X":-3.9369,"Y":-1.0799,"type":"T"},{"X":-3.8748,"Y":-1.807,"type":"T"},{"X":-4.6317,"Y":-2.3037,"type":"T"},{"X":-3.8946,"Y":-1.987,"type":"T"},{"X":-4.0465,"Y":-1.6225,"type":"T"},{"X":-3.3696,"Y":-1.477,"type":"T"},{"X":-4.8247,"Y":-3.0521,"type":"T"},{"X":-3.4536,"Y":-1.8123,"type":"T"},{"X":-3.4778,"Y":-1.6302,"type":"T"},{"X":2.2499,"Y":-0.9517,"type":"T"},{"X":-3.4857,"Y":-1.3171,"type":"T"},{"X":-3.5457,"Y":-1.9389,"type":"T"},{"X":-4.3729,"Y":-1.3427,"type":"T"},{"X":-4.4807,"Y":-1.9921,"type":"T"},{"X":-4.3545,"Y":-1.7432,"type":"T"},{"X":-4.6881,"Y":-1.6541,"type":"T"},{"X":-4.0119,"Y":-1.8089,"type":"T"},{"X":-4.735,"Y":-1.7113,"type":"T"},{"X":-3.3264,"Y":-2.0809,"type":"T"},{"X":-4.0489,"Y":-2.0722,"type":"T"},{"X":-2.6451,"Y":-1.5984,"type":"T"},{"X":-4.4308,"Y":-1.9671,"type":"T"},{"X":-2.7125,"Y":-2.0694,"type":"T"},{"X":-4.3868,"Y":-0.6168,"type":"T"},{"X":-2.7411,"Y":-2.499,"type":"T"},{"X":-3.7381,"Y":-1.9307,"type":"T"},{"X":-3.3884,"Y":-2.2366,"type":"T"},{"X":-4.4377,"Y":-1.4003,"type":"T"},{"X":-2.8221,"Y":-0.3475,"type":"T"},{"X":-4.5024,"Y":-1.6651,"type":"T"},{"X":-4.3041,"Y":-1.849,"type":"T"},{"X":-4.2384,"Y":-1.1662,"type":"T"},{"X":-3.9099,"Y":-1.7644,"type":"T"},{"X":-4.1506,"Y":-2.0313,"type":"T"},{"X":-3.3952,"Y":-2.2893,"type":"T"},{"X":-3.6688,"Y":-1.7567,"type":"T"},{"X":-4.536,"Y":-1.6124,"type":"T"},{"X":-3.6809,"Y":-1.5274,"type":"T"},{"X":-3.0179,"Y":-2.525,"type":"T"},{"X":-3.6633,"Y":-1.6501,"type":"T"},{"X":-3.3831,"Y":-2.3441,"type":"T"},{"X":-2.4004,"Y":-2.0152,"type":"T"},{"X":-4.0936,"Y":-1.659,"type":"T"},{"X":-3.7287,"Y":-2.7226,"type":"T"},{"X":-4.862,"Y":-1.0726,"type":"T"},{"X":-4.8026,"Y":-0.8072,"type":"T"},{"X":-3.9278,"Y":-1.5529,"type":"T"},{"X":-5.4684,"Y":-0.827,"type":"T"},{"X":-2.0072,"Y":-2.6959,"type":"T"},{"X":-4.4269,"Y":-0.9505,"type":"T"},{"X":-3.7358,"Y":-1.9074,"type":"T"},{"X":-3.7824,"Y":-1.8013,"type":"T"},{"X":-4.3617,"Y":-1.4872,"type":"T"},{"X":-4.1178,"Y":-1.9086,"type":"T"},{"X":-3.5272,"Y":-1.1571,"type":"T"},{"X":0.5353,"Y":-2.3068,"type":"T"},{"X":-4.8271,"Y":-1.5981,"type":"T"},{"X":-3.6071,"Y":-1.9221,"type":"T"},{"X":-4.214,"Y":-2.0936,"type":"T"},{"X":-2.4715,"Y":-1.8307,"type":"T"},{"X":-3.9887,"Y":-1.8905,"type":"T"},{"X":-4.2464,"Y":-1.721,"type":"T"},{"X":-2.6057,"Y":-2.1502,"type":"T"},{"X":-3.8088,"Y":-2.5945,"type":"T"},{"X":-4.7895,"Y":-1.5978,"type":"T"},{"X":-3.7605,"Y":-1.4471,"type":"T"},{"X":-2.0827,"Y":-1.5053,"type":"T"},{"X":-4.8493,"Y":-1.5119,"type":"T"},{"X":-4.4179,"Y":-1.229,"type":"T"},{"X":-3.0237,"Y":-1.0993,"type":"T"},{"X":-3.905,"Y":-1.8886,"type":"T"},{"X":-2.6758,"Y":-1.7781,"type":"T"},{"X":-4.1816,"Y":-1.8327,"type":"T"},{"X":-3.8168,"Y":-1.7235,"type":"T"},{"X":-3.5204,"Y":-1.434,"type":"T"},{"X":-2.968,"Y":-1.5145,"type":"T"},{"X":-3.5833,"Y":-2.1306,"type":"T"},{"X":-4.0304,"Y":-2.0875,"type":"T"},{"X":-4.0509,"Y":-2.3075,"type":"T"},{"X":-3.0625,"Y":-1.7561,"type":"T"},{"X":-3.8495,"Y":-1.9808,"type":"T"},{"X":-3.6378,"Y":-2.3576,"type":"T"},{"X":-2.6537,"Y":-1.6773,"type":"T"},{"X":-3.5538,"Y":-1.2394,"type":"T"},{"X":-3.21,"Y":-1.7143,"type":"T"},{"X":-4.1308,"Y":-2.078,"type":"T"},{"X":-5.0727,"Y":-1.0079,"type":"T"},{"X":-4.2546,"Y":-1.8051,"type":"T"},{"X":-4.0244,"Y":-1.5343,"type":"T"},{"X":-2.3763,"Y":-2.1187,"type":"T"},{"X":-4.1213,"Y":-0.9696,"type":"T"},{"X":-2.8373,"Y":-2.04,"type":"T"},{"X":-2.212,"Y":-1.938,"type":"T"},{"X":-3.5245,"Y":-2.3886,"type":"T"},{"X":-3.0536,"Y":-1.7144,"type":"T"},{"X":-3.6998,"Y":-1.9141,"type":"T"},{"X":-4.2109,"Y":-1.5474,"type":"T"},{"X":-4.0659,"Y":-1.8051,"type":"T"},{"X":-4.1348,"Y":-2.0765,"type":"T"},{"X":-2.5696,"Y":-1.7377,"type":"T"},{"X":-3.7897,"Y":-1.2287,"type":"T"},{"X":-3.4724,"Y":-1.471,"type":"T"},{"X":-4.2199,"Y":-1.19,"type":"T"},{"X":-2.6065,"Y":-2.1788,"type":"T"},{"X":-3.5745,"Y":-1.5809,"type":"T"},{"X":-4.1669,"Y":-2.5303,"type":"T"},{"X":-3.5869,"Y":-1.7246,"type":"T"},{"X":-2.8822,"Y":-2.1928,"type":"T"},{"X":-4.3559,"Y":-1.1939,"type":"T"},{"X":-4.0481,"Y":-2.2886,"type":"T"},{"X":-4.04,"Y":-2.1626,"type":"T"},{"X":-2.5791,"Y":-1.6686,"type":"T"},{"X":-3.1662,"Y":-1.8444,"type":"T"},{"X":-3.5397,"Y":-0.8094,"type":"T"},{"X":-3.132,"Y":-1.8477,"type":"T"},{"X":-4.3372,"Y":-1.0989,"type":"T"},{"X":-3.599,"Y":-1.6295,"type":"T"},{"X":-5.6803,"Y":-2.7459,"type":"T"},{"X":-4.4743,"Y":-2.4807,"type":"T"},{"X":-3.5618,"Y":-1.6426,"type":"T"},{"X":-4.3652,"Y":-1.9715,"type":"T"},{"X":-4.1862,"Y":-1.8001,"type":"T"},{"X":-4.9155,"Y":-2.3199,"type":"T"},{"X":-3.8826,"Y":-1.8742,"type":"T"},{"X":-4.355,"Y":-3.1824,"type":"T"},{"X":-3.7974,"Y":-1.6993,"type":"T"},{"X":-4.0105,"Y":-1.4139,"type":"T"},{"X":-4.5547,"Y":-2.4714,"type":"T"},{"X":-2.2356,"Y":-1.8026,"type":"T"},{"X":-2.2433,"Y":-2.4618,"type":"T"},{"X":-3.9028,"Y":-2.1642,"type":"T"},{"X":-4.3962,"Y":0.3232,"type":"T"},{"X":-4.2529,"Y":-1.7532,"type":"T"},{"X":-3.4397,"Y":-1.4226,"type":"T"},{"X":-3.8056,"Y":-2.001,"type":"T"},{"X":-4.1648,"Y":-1.0007,"type":"T"},{"X":-2.7168,"Y":-1.7097,"type":"T"},{"X":-3.7221,"Y":-1.4895,"type":"T"},{"X":-3.6968,"Y":-1.9428,"type":"T"},{"X":-2.5117,"Y":-1.2398,"type":"T"},{"X":-3.6067,"Y":-1.9455,"type":"T"},{"X":-4.5564,"Y":-1.8086,"type":"T"},{"X":-3.7156,"Y":-2.0795,"type":"T"},{"X":-3.8703,"Y":-1.6983,"type":"T"},{"X":-3.6418,"Y":-1.7698,"type":"T"},{"X":-3.6804,"Y":-1.3568,"type":"T"},{"X":-4.8488,"Y":-1.984,"type":"T"},{"X":-4.0892,"Y":-1.9088,"type":"T"},{"X":-3.747,"Y":-0.6935,"type":"T"},{"X":-4.3803,"Y":-1.8075,"type":"T"},{"X":-3.9062,"Y":-2.7374,"type":"T"},{"X":-3.7197,"Y":-1.8235,"type":"T"},{"X":-3.6431,"Y":-2.4914,"type":"T"},{"X":-4.1564,"Y":-1.8674,"type":"T"},{"X":-3.9642,"Y":-1.6663,"type":"T"},{"X":-4.0831,"Y":-2.1781,"type":"T"},{"X":-3.8907,"Y":-1.3869,"type":"T"},{"X":-3.616,"Y":-2.1315,"type":"T"},{"X":-4.1582,"Y":-1.866,"type":"T"},{"X":-4.112,"Y":-1.1384,"type":"T"},{"X":-3.0361,"Y":-2.1715,"type":"T"},{"X":-3.5473,"Y":-1.9515,"type":"T"},{"X":-0.6027,"Y":-1.0456,"type":"T"},{"X":-4.6416,"Y":-0.0937,"type":"T"},{"X":-3.594,"Y":-1.7265,"type":"T"},{"X":-3.627,"Y":-2.0157,"type":"T"},{"X":-4.3646,"Y":-1.1329,"type":"T"},{"X":-4.4852,"Y":-1.4451,"type":"T"},{"X":-4.0128,"Y":-2.0598,"type":"T"},{"X":-3.4076,"Y":-1.6166,"type":"T"},{"X":-4.2302,"Y":-1.0718,"type":"T"},{"X":-4.0881,"Y":-2.0583,"type":"T"},{"X":-2.7595,"Y":-2.5624,"type":"T"},{"X":-3.4647,"Y":-2.7017,"type":"T"},{"X":-3.4815,"Y":-0.7037,"type":"T"},{"X":-4.1932,"Y":-2.0269,"type":"T"},{"X":-4.7677,"Y":-1.724,"type":"T"},{"X":-2.3806,"Y":-1.6762,"type":"T"},{"X":-2.8251,"Y":-1.8071,"type":"T"},{"X":-0.4721,"Y":-1.3343,"type":"T"},{"X":-3.4303,"Y":-2.212,"type":"T"},{"X":-3.8693,"Y":-2.0769,"type":"T"},{"X":-3.3646,"Y":-1.1286,"type":"T"},{"X":-2.4283,"Y":-1.618,"type":"T"},{"X":-3.4563,"Y":-2.0786,"type":"T"},{"X":-3.3086,"Y":-2.0975,"type":"T"},{"X":-3.7803,"Y":-1.7489,"type":"T"},{"X":-2.6927,"Y":-1.8301,"type":"T"},{"X":-3.1018,"Y":-1.6041,"type":"T"},{"X":-3.17,"Y":-2.9559,"type":"T"},{"X":-4.2063,"Y":-1.5708,"type":"T"},{"X":-4.0025,"Y":-1.7741,"type":"T"},{"X":-3.8985,"Y":-1.5818,"type":"T"},{"X":-2.5976,"Y":-1.3535,"type":"T"},{"X":-4.3196,"Y":-1.722,"type":"T"},{"X":-4.2488,"Y":-1.4689,"type":"T"},{"X":-2.6003,"Y":-0.5396,"type":"T"},{"X":-4.3781,"Y":-1.816,"type":"T"},{"X":-4.1631,"Y":-2.2586,"type":"T"},{"X":-1.9682,"Y":-2.8076,"type":"T"},{"X":-3.5114,"Y":-2.0506,"type":"T"},{"X":-3.3518,"Y":-1.2919,"type":"T"},{"X":-3.7278,"Y":-0.8598,"type":"T"},{"X":-3.3528,"Y":-1.9797,"type":"T"},{"X":-3.3641,"Y":-1.4135,"type":"T"},{"X":-4.3194,"Y":-1.6832,"type":"T"},{"X":-4.2,"Y":-1.698,"type":"T"},{"X":-4.043,"Y":-2.474,"type":"T"},{"X":-4.0619,"Y":-1.909,"type":"T"},{"X":-3.1992,"Y":-0.4766,"type":"T"},{"X":-2.4943,"Y":-2.4206,"type":"T"},{"X":-3.8467,"Y":-1.7391,"type":"T"},{"X":-3.5874,"Y":-2.1774,"type":"T"},{"X":-3.2711,"Y":-1.5929,"type":"T"},{"X":-3.5793,"Y":-1.5942,"type":"T"},{"X":-3.9145,"Y":-1.7545,"type":"T"},{"X":-3.8917,"Y":-2.4702,"type":"T"},{"X":-4.5895,"Y":-2.5817,"type":"T"},{"X":-4.4246,"Y":-1.6557,"type":"T"},{"X":-2.487,"Y":-1.8367,"type":"T"},{"X":-4.2579,"Y":-1.7005,"type":"T"},{"X":-4.0712,"Y":-2.7204,"type":"T"},{"X":-3.9177,"Y":-1.5525,"type":"T"},{"X":-2.2545,"Y":-1.3592,"type":"T"},{"X":-3.6371,"Y":-2.7093,"type":"T"},{"X":-2.5002,"Y":-1.6769,"type":"T"},{"X":-2.6203,"Y":-2.4599,"type":"T"},{"X":-3.5969,"Y":-1.6418,"type":"T"},{"X":-4.0057,"Y":-1.3452,"type":"T"},{"X":-4.0934,"Y":-1.4007,"type":"T"},{"X":-3.7272,"Y":-0.8011,"type":"T"},{"X":-4.4215,"Y":-1.7334,"type":"T"},{"X":-3.4647,"Y":-1.8852,"type":"T"},{"X":-3.6865,"Y":-1.9045,"type":"T"},{"X":-3.5729,"Y":-1.8275,"type":"T"},{"X":-3.7498,"Y":-1.5075,"type":"T"},{"X":-3.8376,"Y":-1.9056,"type":"T"},{"X":-2.8281,"Y":-1.6444,"type":"T"},{"X":-2.803,"Y":-1.7691,"type":"T"},{"X":-4.2482,"Y":-2.0869,"type":"T"},{"X":-4.4687,"Y":-2.0466,"type":"T"},{"X":-4.3727,"Y":-1.8818,"type":"T"},{"X":-4.1945,"Y":-1.5937,"type":"T"},{"X":-3.8023,"Y":-2.0558,"type":"T"},{"X":-4.3032,"Y":-1.1051,"type":"T"},{"X":-2.3683,"Y":-2.056,"type":"T"},{"X":-3.2814,"Y":-2.2157,"type":"T"},{"X":-4.3263,"Y":-2.1104,"type":"T"},{"X":-4.0644,"Y":-1.269,"type":"T"},{"X":-4.8103,"Y":-1.9847,"type":"T"},{"X":-4.3543,"Y":-2.1611,"type":"T"},{"X":-4.0317,"Y":-1.4969,"type":"T"},{"X":-2.6776,"Y":-2.0975,"type":"T"},{"X":-3.5718,"Y":-1.8067,"type":"T"},{"X":-4.327,"Y":-1.7015,"type":"T"},{"X":-3.865,"Y":-2.586,"type":"T"},{"X":-4.2868,"Y":-1.5937,"type":"T"},{"X":-3.9029,"Y":-1.6658,"type":"T"},{"X":-4.3049,"Y":-1.4904,"type":"T"},{"X":-4.0643,"Y":-0.7484,"type":"T"},{"X":-3.9555,"Y":-1.4959,"type":"T"},{"X":-2.491,"Y":-2.9953,"type":"T"},{"X":-2.228,"Y":-1.6859,"type":"T"},{"X":-3.7871,"Y":-2.282,"type":"T"},{"X":-3.8665,"Y":-0.4023,"type":"T"},{"X":-3.9937,"Y":-1.2349,"type":"T"},{"X":-4.4525,"Y":-1.4726,"type":"T"},{"X":-3.628,"Y":-2.2703,"type":"T"},{"X":-4.4725,"Y":-1.5636,"type":"T"},{"X":-3.8097,"Y":-2.2889,"type":"T"},{"X":-3.0186,"Y":-1.3684,"type":"T"},{"X":-3.5299,"Y":-1.5716,"type":"T"},{"X":-3.8114,"Y":-1.8417,"type":"T"},{"X":-4.3633,"Y":-1.445,"type":"T"},{"X":-3.3102,"Y":-2.1476,"type":"T"},{"X":-4.2257,"Y":-2.0264,"type":"T"},{"X":-4.5484,"Y":-0.6335,"type":"T"},{"X":-3.9046,"Y":-1.7197,"type":"T"},{"X":-3.7369,"Y":-1.8453,"type":"T"},{"X":-2.8954,"Y":-2.1145,"type":"T"},{"X":-4.2127,"Y":-1.9401,"type":"T"},{"X":-4.5301,"Y":-0.752,"type":"T"},{"X":-2.6768,"Y":-1.8699,"type":"T"},{"X":-3.3489,"Y":-1.692,"type":"T"},{"X":-4.3206,"Y":-1.1298,"type":"T"},{"X":-3.7541,"Y":-1.4153,"type":"T"},{"X":-3.5302,"Y":-1.3815,"type":"T"},{"X":-4.0715,"Y":-1.4689,"type":"T"},{"X":-2.26,"Y":-1.5769,"type":"T"},{"X":-3.5952,"Y":-1.7728,"type":"T"},{"X":-4.6017,"Y":-2.1296,"type":"T"},{"X":-4.3594,"Y":-1.6955,"type":"T"},{"X":-3.799,"Y":-0.8655,"type":"T"},{"X":-4.3245,"Y":-2.0566,"type":"T"},{"X":-4.0568,"Y":-1.4263,"type":"T"},{"X":-3.8594,"Y":-1.5211,"type":"T"},{"X":-3.5812,"Y":-1.6238,"type":"T"},{"X":-3.7112,"Y":-1.7982,"type":"T"},{"X":-4.1143,"Y":-2.0907,"type":"T"},{"X":-4.5021,"Y":-2.4103,"type":"T"},{"X":-3.8736,"Y":-1.8357,"type":"T"},{"X":-2.0387,"Y":-2.0409,"type":"T"},{"X":-2.902,"Y":-1.3998,"type":"T"},{"X":-4.1046,"Y":-1.7185,"type":"T"},{"X":-3.2557,"Y":-1.5825,"type":"T"},{"X":-4.9712,"Y":-0.7933,"type":"T"},{"X":-4.1054,"Y":-2.5219,"type":"T"},{"X":-3.3091,"Y":-2.3586,"type":"T"},{"X":-3.8749,"Y":-2.0813,"type":"T"},{"X":-3.7721,"Y":-2.2631,"type":"T"},{"X":-3.0331,"Y":-2.1847,"type":"T"},{"X":-4.3678,"Y":-1.4564,"type":"T"},{"X":-3.7726,"Y":-0.7164,"type":"T"},{"X":-4.8264,"Y":-1.4189,"type":"T"},{"X":-3.8882,"Y":-0.2629,"type":"T"},{"X":-4.1234,"Y":-1.0152,"type":"T"},{"X":-3.8701,"Y":-2.1241,"type":"T"},{"X":-5.4859,"Y":-1.463,"type":"T"},{"X":-4.4577,"Y":-1.7524,"type":"T"},{"X":-4.2265,"Y":-2.6685,"type":"T"},{"X":-3.827,"Y":-2.4503,"type":"T"},{"X":-4.2645,"Y":-1.9085,"type":"T"},{"X":-3.5615,"Y":-1.446,"type":"T"},{"X":-3.3977,"Y":-1.2205,"type":"T"},{"X":-3.9924,"Y":-0.8731,"type":"T"},{"X":-4.1784,"Y":-2.1465,"type":"T"},{"X":-2.2803,"Y":-1.6534,"type":"T"},{"X":-4.2208,"Y":-1.2609,"type":"T"},{"X":-3.84,"Y":-2.369,"type":"T"},{"X":-4.287,"Y":-0.8061,"type":"T"},{"X":-4.524,"Y":-1.9071,"type":"T"},{"X":-4.5223,"Y":-2.4027,"type":"T"},{"X":-3.7459,"Y":-2.122,"type":"T"},{"X":-4.2733,"Y":-1.6869,"type":"T"},{"X":-4.1237,"Y":-2.3604,"type":"T"},{"X":-3.6632,"Y":-1.6752,"type":"T"},{"X":-3.4868,"Y":-1.9004,"type":"T"},{"X":-4.083,"Y":-1.6208,"type":"T"},{"X":-3.4528,"Y":-2.2092,"type":"T"},{"X":-3.9388,"Y":-1.4543,"type":"T"},{"X":-2.9941,"Y":-1.8538,"type":"T"},{"X":-3.0896,"Y":-2.4647,"type":"T"},{"X":-2.91,"Y":-2.4744,"type":"T"},{"X":-3.7969,"Y":-1.8945,"type":"T"},{"X":-3.5561,"Y":-2.4029,"type":"T"},{"X":-3.8089,"Y":-1.4284,"type":"T"},{"X":-3.919,"Y":-1.9089,"type":"T"},{"X":-4.0978,"Y":-2.2478,"type":"T"},{"X":-2.7663,"Y":-1.7635,"type":"T"},{"X":-4.72,"Y":-0.886,"type":"T"},{"X":-3.7152,"Y":-1.5952,"type":"T"},{"X":-2.8312,"Y":-1.6989,"type":"T"},{"X":-3.5857,"Y":-1.7867,"type":"T"},{"X":-2.054,"Y":-1.9533,"type":"T"},{"X":-3.786,"Y":-2.0151,"type":"T"},{"X":-4.6897,"Y":-1.78,"type":"T"},{"X":-3.1675,"Y":-2.507,"type":"T"},{"X":-3.7051,"Y":-1.9313,"type":"T"},{"X":-4.8719,"Y":-1.2076,"type":"T"},{"X":-4.5318,"Y":-1.1974,"type":"T"},{"X":-3.8226,"Y":-1.6786,"type":"T"},{"X":-3.9731,"Y":-1.7539,"type":"T"},{"X":-3.9919,"Y":-2.3437,"type":"T"},{"X":-4.1247,"Y":-1.486,"type":"T"},{"X":-2.9557,"Y":-1.495,"type":"T"},{"X":-4.258,"Y":-1.9918,"type":"T"},{"X":-4.2318,"Y":-1.602,"type":"T"},{"X":-4.0745,"Y":-2.1144,"type":"T"},{"X":-3.9263,"Y":-2.5669,"type":"T"},{"X":-4.2748,"Y":-1.4549,"type":"T"},{"X":-4.463,"Y":-2.255,"type":"T"},{"X":-3.7101,"Y":-2.3041,"type":"T"},{"X":-3.9427,"Y":-1.7278,"type":"T"},{"X":-2.6446,"Y":-1.8725,"type":"T"},{"X":-3.5941,"Y":-0.6722,"type":"T"},{"X":-4.2155,"Y":-0.6875,"type":"T"},{"X":-3.9,"Y":-1.0522,"type":"T"},{"X":-4.6542,"Y":-1.2719,"type":"T"},{"X":-4.1625,"Y":-1.7603,"type":"T"},{"X":-4.2319,"Y":-1.6864,"type":"T"},{"X":-1.8027,"Y":-2.1621,"type":"T"},{"X":-4.3643,"Y":-2.0681,"type":"T"},{"X":-2.6922,"Y":-1.5619,"type":"T"},{"X":-2.9674,"Y":-2.3174,"type":"T"},{"X":-3.943,"Y":-2.2395,"type":"T"},{"X":-3.7096,"Y":-1.9022,"type":"T"},{"X":-4.5256,"Y":-1.1777,"type":"T"},{"X":-3.9663,"Y":-1.8372,"type":"T"},{"X":-4.1803,"Y":-0.7086,"type":"T"},{"X":-4.1411,"Y":-0.5251,"type":"T"},{"X":-2.8879,"Y":-1.7065,"type":"T"},{"X":-4.5839,"Y":-0.9999,"type":"T"},{"X":-4.3053,"Y":-1.4633,"type":"T"},{"X":-3.8636,"Y":-2.516,"type":"T"},{"X":-1.7031,"Y":-1.7124,"type":"T"},{"X":-3.1362,"Y":-2.094,"type":"T"},{"X":-3.9737,"Y":-0.6717,"type":"T"},{"X":-4.3034,"Y":-2.2891,"type":"T"},{"X":-4.2732,"Y":-1.4305,"type":"T"},{"X":-3.8997,"Y":-2.0893,"type":"T"},{"X":-3.8833,"Y":-2.1398,"type":"T"},{"X":-3.702,"Y":-1.5908,"type":"T"},{"X":-2.666,"Y":-1.6768,"type":"T"},{"X":-4.5042,"Y":-1.4618,"type":"T"},{"X":-3.8806,"Y":-1.5759,"type":"T"},{"X":-3.0317,"Y":-0.4664,"type":"T"},{"X":-3.401,"Y":-1.5251,"type":"T"},{"X":-3.3066,"Y":-2.4726,"type":"T"},{"X":-4.137,"Y":-0.6578,"type":"T"},{"X":-3.1042,"Y":-1.9914,"type":"T"},{"X":-3.1773,"Y":-1.7815,"type":"T"},{"X":-2.194,"Y":-1.839,"type":"T"},{"X":-2.6807,"Y":-1.2258,"type":"T"},{"X":-4.0575,"Y":-2.2672,"type":"T"},{"X":-4.0339,"Y":-1.6285,"type":"T"},{"X":-4.1835,"Y":-2.1524,"type":"T"},{"X":-3.4573,"Y":-1.6313,"type":"T"},{"X":-4.1222,"Y":-1.8483,"type":"T"},{"X":-4.6046,"Y":-2.1874,"type":"T"},{"X":-2.5324,"Y":-2.3897,"type":"T"},{"X":-4.5019,"Y":-2.1681,"type":"T"},{"X":-4.1121,"Y":-2.2581,"type":"T"},{"X":-2.9312,"Y":-1.426,"type":"T"},{"X":-3.3676,"Y":-1.8342,"type":"T"},{"X":-3.724,"Y":-1.4937,"type":"T"},{"X":-4.264,"Y":-1.7806,"type":"T"},{"X":-4.3615,"Y":-1.3472,"type":"T"},{"X":-3.6741,"Y":-1.6427,"type":"T"},{"X":-3.8351,"Y":-2.0996,"type":"T"},{"X":-2.129,"Y":-1.4781,"type":"T"},{"X":-4.5949,"Y":-1.5723,"type":"T"},{"X":-3.9271,"Y":-1.3551,"type":"T"},{"X":-4.2357,"Y":-1.3743,"type":"T"},{"X":-4.128,"Y":-1.6019,"type":"T"},{"X":-4.0264,"Y":-1.2213,"type":"T"},{"X":-3.609,"Y":-1.6011,"type":"T"},{"X":-3.467,"Y":-1.5402,"type":"T"},{"X":-2.5448,"Y":-1.6777,"type":"T"},{"X":-4.1779,"Y":-1.5487,"type":"T"},{"X":-4.0812,"Y":-1.3769,"type":"T"},{"X":-4.492,"Y":-0.9635,"type":"T"},{"X":-3.099,"Y":-2.4212,"type":"T"},{"X":-4.3927,"Y":-2.1129,"type":"T"},{"X":-3.4715,"Y":-2.0857,"type":"T"},{"X":-4.6394,"Y":-1.0108,"type":"T"},{"X":-3.7685,"Y":-1.7888,"type":"T"},{"X":-3.5396,"Y":-1.7497,"type":"T"},{"X":-4.1458,"Y":-1.7172,"type":"T"},{"X":-4.2301,"Y":-0.8071,"type":"T"},{"X":-4.2286,"Y":-1.7552,"type":"T"},{"X":-0.9381,"Y":-2.8644,"type":"T"},{"X":-4.0394,"Y":-2.108,"type":"T"},{"X":-3.86,"Y":-1.7217,"type":"T"},{"X":-2.4871,"Y":-2.2381,"type":"T"},{"X":-3.8865,"Y":-1.5625,"type":"T"},{"X":-2.9565,"Y":-1.8122,"type":"T"},{"X":0.3488,"Y":-1.5658,"type":"T"},{"X":-3.5014,"Y":-1.3935,"type":"T"},{"X":-2.612,"Y":-1.6062,"type":"T"},{"X":-4.1091,"Y":-1.3406,"type":"T"},{"X":-2.9386,"Y":-2.3165,"type":"T"},{"X":-2.9019,"Y":-1.3894,"type":"T"},{"X":-1.8807,"Y":-2.1917,"type":"T"},{"X":-3.4407,"Y":-2.0009,"type":"T"},{"X":-2.5024,"Y":-1.1171,"type":"T"},{"X":-3.4443,"Y":-1.7555,"type":"T"},{"X":-3.6761,"Y":-1.2654,"type":"T"},{"X":-4.1254,"Y":-1.3469,"type":"T"},{"X":0.4464,"Y":-1.0189,"type":"T"},{"X":-2.2598,"Y":-2.0782,"type":"T"},{"X":-3.5294,"Y":-2.7572,"type":"T"},{"X":-3.7293,"Y":-1.7109,"type":"T"},{"X":-4.3168,"Y":-2.0852,"type":"T"},{"X":-4.639,"Y":-1.3316,"type":"T"},{"X":-4.2721,"Y":-1.464,"type":"T"},{"X":-3.6671,"Y":-1.6818,"type":"T"},{"X":-4.4898,"Y":-1.5905,"type":"T"},{"X":-3.6775,"Y":-1.6248,"type":"T"},{"X":-4.076,"Y":-1.4318,"type":"T"},{"X":-3.2643,"Y":-1.6532,"type":"T"},{"X":-4.1749,"Y":-2.1971,"type":"T"},{"X":-4.2887,"Y":-2.0722,"type":"T"},{"X":-3.5986,"Y":-1.8437,"type":"T"},{"X":-2.7114,"Y":-2.4421,"type":"T"},{"X":-4.1098,"Y":-1.4,"type":"T"},{"X":-4.4669,"Y":-0.9186,"type":"T"},{"X":-3.8123,"Y":-1.4881,"type":"T"},{"X":-3.8033,"Y":-1.175,"type":"T"},{"X":-3.9275,"Y":-2.9309,"type":"T"},{"X":-5.2736,"Y":-1.6046,"type":"T"},{"X":-3.8945,"Y":-2.2466,"type":"T"},{"X":-3.2383,"Y":-2.0599,"type":"T"},{"X":-3.9873,"Y":-1.0712,"type":"T"},{"X":-3.4169,"Y":-1.9271,"type":"T"},{"X":-3.736,"Y":-1.9445,"type":"T"},{"X":-4.2794,"Y":-1.7526,"type":"T"},{"X":-2.0489,"Y":-0.6379,"type":"T"},{"X":-3.2772,"Y":-1.6487,"type":"T"},{"X":-4.27,"Y":-1.5585,"type":"T"},{"X":-3.9846,"Y":-1.7048,"type":"T"},{"X":-4.6799,"Y":-1.0869,"type":"T"},{"X":-4.0103,"Y":-1.5852,"type":"T"},{"X":-4.3934,"Y":-1.5482,"type":"T"},{"X":-3.7398,"Y":-2.9143,"type":"T"},{"X":-3.8798,"Y":-2.3041,"type":"T"},{"X":-4.2948,"Y":-0.9145,"type":"T"},{"X":-3.9511,"Y":-1.5231,"type":"T"},{"X":-4.3372,"Y":-0.4162,"type":"T"},{"X":-4.0602,"Y":-1.8385,"type":"T"},{"X":-3.7183,"Y":-1.8264,"type":"T"},{"X":1.2135,"Y":-1.3187,"type":"T"},{"X":-4.1449,"Y":-1.1318,"type":"T"},{"X":-3.969,"Y":-3.1035,"type":"Body"},{"X":-4.1602,"Y":-4.4889,"type":"Body"},{"X":-2.6246,"Y":-4.194,"type":"Body"},{"X":-3.7904,"Y":-3.7943,"type":"Body"},{"X":-3.797,"Y":-3.4678,"type":"Body"},{"X":-2.0877,"Y":-4.4333,"type":"Body"},{"X":-3.0589,"Y":-2.1602,"type":"Body"},{"X":-2.478,"Y":-3.9045,"type":"Body"},{"X":-4.0037,"Y":-4.5653,"type":"Body"},{"X":-4.5738,"Y":-2.6293,"type":"Body"},{"X":-2.1497,"Y":-4.162,"type":"Body"},{"X":-3.9481,"Y":-3.2268,"type":"Body"},{"X":-3.1302,"Y":-3.6307,"type":"Body"},{"X":-3.1697,"Y":-3.8044,"type":"Body"},{"X":-2.1595,"Y":-4.0918,"type":"Body"},{"X":0.3294,"Y":-3.5063,"type":"Body"},{"X":-3.9771,"Y":-3.6787,"type":"Body"},{"X":-2.7657,"Y":-2.8179,"type":"Body"},{"X":-3.6211,"Y":-3.0056,"type":"Body"},{"X":-3.1167,"Y":-3.4991,"type":"Body"},{"X":-2.5687,"Y":-3.3913,"type":"Body"},{"X":-4.3674,"Y":-1.4901,"type":"Body"},{"X":-3.7518,"Y":-3.409,"type":"Body"},{"X":-1.1132,"Y":-4.177,"type":"Body"},{"X":-3.8268,"Y":-3.4304,"type":"Body"},{"X":-3.2632,"Y":-3.3226,"type":"Body"},{"X":-3.4834,"Y":-3.8107,"type":"Body"},{"X":-4.391,"Y":-2.4279,"type":"Body"},{"X":-3.7455,"Y":-2.8484,"type":"Body"},{"X":-3.7221,"Y":-3.1395,"type":"Body"},{"X":-3.9428,"Y":-4.0154,"type":"Body"},{"X":-3.2898,"Y":-3.3483,"type":"Body"},{"X":-1.8494,"Y":-4.4304,"type":"Body"},{"X":-5.1247,"Y":-3.3887,"type":"Body"},{"X":2.274,"Y":-3.4254,"type":"Body"},{"X":-3.8208,"Y":-2.757,"type":"Body"},{"X":-3.2137,"Y":-4.1152,"type":"Body"},{"X":-3.428,"Y":-3.418,"type":"Body"},{"X":-3.5971,"Y":-3.1709,"type":"Body"},{"X":-3.315,"Y":-3.241,"type":"Body"},{"X":-4.476,"Y":-2.2892,"type":"Body"},{"X":-0.9016,"Y":-2.3254,"type":"Body"},{"X":-3.7719,"Y":-3.253,"type":"Body"},{"X":0.3699,"Y":-3.4441,"type":"Body"},{"X":-3.7399,"Y":-2.9464,"type":"Body"},{"X":-1.8465,"Y":-3.8563,"type":"Body"},{"X":-3.9496,"Y":-2.7738,"type":"Body"},{"X":-4.639,"Y":-3.4517,"type":"Body"},{"X":-3.733,"Y":-3.0511,"type":"Body"},{"X":-3.4183,"Y":-3.1521,"type":"Body"},{"X":-3.6338,"Y":-2.9936,"type":"Body"},{"X":-2.3643,"Y":-4.4392,"type":"Body"},{"X":-3.9029,"Y":-2.4478,"type":"Body"},{"X":-3.344,"Y":-3.89,"type":"Body"},{"X":-3.6375,"Y":-2.6696,"type":"Body"},{"X":-3.795,"Y":-2.9061,"type":"Body"},{"X":-3.9747,"Y":-2.8078,"type":"Body"},{"X":-3.5197,"Y":-2.4342,"type":"Body"},{"X":-3.8015,"Y":-3.3365,"type":"Body"},{"X":-3.1935,"Y":-3.3738,"type":"Body"},{"X":-2.8653,"Y":-2.6803,"type":"Body"},{"X":-3.6448,"Y":-2.408,"type":"Body"},{"X":-3.3644,"Y":-3.4467,"type":"Body"},{"X":-3.5979,"Y":-2.5606,"type":"Body"},{"X":-3.5753,"Y":-3.1306,"type":"Body"},{"X":-3.6274,"Y":-3.4631,"type":"Body"},{"X":-2.5834,"Y":-4.1117,"type":"Body"},{"X":-3.5051,"Y":-3.5037,"type":"Body"},{"X":-3.5011,"Y":-4.1459,"type":"Body"},{"X":-3.855,"Y":-3.5986,"type":"Body"},{"X":-3.6536,"Y":-3.2177,"type":"Body"},{"X":-3.5496,"Y":-2.9442,"type":"Body"},{"X":-2.3736,"Y":-3.7286,"type":"Body"},{"X":-3.7558,"Y":-2.6082,"type":"Body"},{"X":-2.3819,"Y":-3.8992,"type":"Body"},{"X":-2.1717,"Y":-4.0461,"type":"Body"},{"X":-3.5394,"Y":-3.083,"type":"Body"},{"X":-3.9303,"Y":-2.7099,"type":"Body"},{"X":-3.933,"Y":-3.5968,"type":"Body"},{"X":-3.3508,"Y":-3.2783,"type":"Body"},{"X":-3.9127,"Y":-3.0588,"type":"Body"},{"X":-3.717,"Y":-2.5359,"type":"Body"},{"X":-3.6639,"Y":-2.5521,"type":"Body"},{"X":-4.1296,"Y":-2.8329,"type":"Body"},{"X":-3.2903,"Y":-2.383,"type":"Body"},{"X":-4.4077,"Y":-2.8153,"type":"Body"},{"X":-3.39,"Y":-2.6111,"type":"Body"},{"X":-3.3995,"Y":-3.7137,"type":"Body"},{"X":-2.8992,"Y":-4.1282,"type":"Body"},{"X":-3.5049,"Y":-3.6924,"type":"Body"},{"X":-3.8271,"Y":-2.8393,"type":"Body"},{"X":-4.6667,"Y":-3.2156,"type":"Body"},{"X":-4.0256,"Y":-4.2262,"type":"Body"},{"X":2.1192,"Y":-4.0548,"type":"Body"},{"X":-3.9066,"Y":-3.1248,"type":"Body"},{"X":-3.5689,"Y":-3.185,"type":"Body"},{"X":-2.9715,"Y":-3.0082,"type":"Body"},{"X":-4.1638,"Y":-2.6272,"type":"Body"},{"X":-3.6297,"Y":-3.3502,"type":"Body"},{"X":-3.9271,"Y":-3.1969,"type":"Body"},{"X":-3.3951,"Y":-2.9827,"type":"Body"},{"X":-3.7268,"Y":-2.5003,"type":"Body"},{"X":-2.9006,"Y":-2.9885,"type":"Body"},{"X":-3.8053,"Y":-3.3335,"type":"Body"},{"X":-3.8742,"Y":-2.0103,"type":"Body"},{"X":-2.9895,"Y":-3.029,"type":"Body"},{"X":-2.9468,"Y":-3.5367,"type":"Body"},{"X":-3.7712,"Y":-3.0292,"type":"Body"},{"X":-4.163,"Y":-3.2728,"type":"Body"},{"X":-3.3659,"Y":-2.8829,"type":"Body"},{"X":-3.9467,"Y":-2.7091,"type":"Body"},{"X":-1.8025,"Y":-3.9419,"type":"Body"},{"X":-3.3977,"Y":-4.4064,"type":"Body"},{"X":-4.0741,"Y":-2.9236,"type":"Body"},{"X":-3.721,"Y":-3.5239,"type":"Body"},{"X":-3.5044,"Y":-2.9755,"type":"Body"},{"X":-3.038,"Y":-2.9778,"type":"Body"},{"X":-3.9746,"Y":-2.6083,"type":"Body"},{"X":-3.9055,"Y":-2.1279,"type":"Body"},{"X":-3.0016,"Y":-4.4062,"type":"Body"},{"X":-3.6469,"Y":-2.7152,"type":"Body"},{"X":-2.1004,"Y":-3.9561,"type":"Body"},{"X":-3.729,"Y":-3.4724,"type":"Body"},{"X":-3.3858,"Y":-3.3725,"type":"Body"},{"X":-3.3557,"Y":-2.5725,"type":"Body"},{"X":-3.4676,"Y":-2.5424,"type":"Body"},{"X":-3.8471,"Y":-3.2754,"type":"Body"},{"X":-3.3002,"Y":-3.7978,"type":"Body"},{"X":-3.8299,"Y":-2.4854,"type":"Body"},{"X":-3.6271,"Y":-2.318,"type":"Body"},{"X":-2.017,"Y":-4.0264,"type":"Body"},{"X":-3.965,"Y":-3.2078,"type":"Body"},{"X":-2.2666,"Y":-4.5284,"type":"Body"},{"X":-2.0546,"Y":-3.6615,"type":"Body"},{"X":-3.4912,"Y":-4.0876,"type":"Body"},{"X":-2.6377,"Y":-3.6904,"type":"Body"},{"X":-3.0883,"Y":-3.2284,"type":"Body"},{"X":-3.3732,"Y":-3.4772,"type":"Body"},{"X":-4.0525,"Y":-2.4716,"type":"Body"},{"X":-3.2938,"Y":-4.0129,"type":"Body"},{"X":-3.4108,"Y":-4.4069,"type":"Body"},{"X":-4.4313,"Y":-3.2886,"type":"Body"},{"X":-3.3894,"Y":-2.8738,"type":"Body"},{"X":-2.1765,"Y":-4.2098,"type":"Body"},{"X":-2.5709,"Y":-3.8516,"type":"Body"},{"X":-3.8628,"Y":-3.3856,"type":"Body"},{"X":-0.9676,"Y":-3.5673,"type":"Body"},{"X":-4.2411,"Y":-3.0191,"type":"Body"},{"X":-4.2364,"Y":-3.0038,"type":"Body"},{"X":-3.5426,"Y":-2.8759,"type":"Body"},{"X":-3.8552,"Y":-3.5879,"type":"Body"},{"X":-3.5828,"Y":-2.4922,"type":"Body"},{"X":-3.8534,"Y":-3.1568,"type":"Body"},{"X":-3.2369,"Y":-3.4984,"type":"Body"},{"X":-4.5274,"Y":-4.0189,"type":"Body"},{"X":-4.0349,"Y":-3.1047,"type":"Body"},{"X":-4.0207,"Y":-2.3923,"type":"Body"},{"X":-2.4002,"Y":-4.0293,"type":"Body"},{"X":-3.0434,"Y":-4.3886,"type":"Body"},{"X":-3.4011,"Y":-3.4632,"type":"Body"},{"X":-3.3571,"Y":-3.3988,"type":"Body"},{"X":-3.9094,"Y":-2.5864,"type":"Body"},{"X":-3.254,"Y":-2.5449,"type":"Body"},{"X":-3.9448,"Y":-3.1724,"type":"Body"},{"X":-2.2596,"Y":-4.4162,"type":"Body"},{"X":-2.9469,"Y":-4.756,"type":"Body"},{"X":-3.3296,"Y":-3.0477,"type":"Body"},{"X":-3.3765,"Y":-3.6683,"type":"Body"},{"X":-2.5635,"Y":-3.4301,"type":"Body"},{"X":-3.8016,"Y":-2.65,"type":"Body"},{"X":-4.0313,"Y":-2.622,"type":"Body"},{"X":-3.8003,"Y":-2.6935,"type":"Body"},{"X":-3.5862,"Y":-3.2609,"type":"Body"},{"X":-2.2926,"Y":-4.2488,"type":"Body"},{"X":-4.4832,"Y":-3.8127,"type":"Body"},{"X":-3.855,"Y":-2.655,"type":"Body"},{"X":-3.0585,"Y":-3.0123,"type":"Body"},{"X":-3.3991,"Y":-3.4472,"type":"Body"},{"X":-3.9904,"Y":-2.5347,"type":"Body"},{"X":-3.7748,"Y":-2.9808,"type":"Body"},{"X":-4.1306,"Y":-2.9378,"type":"Body"},{"X":-3.5001,"Y":-3.4943,"type":"Body"},{"X":-3.4634,"Y":-3.786,"type":"Body"},{"X":-3.1684,"Y":-2.8923,"type":"Body"},{"X":-2.108,"Y":-4.0718,"type":"Body"},{"X":-2.8633,"Y":-2.9578,"type":"Body"},{"X":-4.2873,"Y":-2.3347,"type":"Body"},{"X":-3.4886,"Y":-2.8804,"type":"Body"},{"X":-4.0882,"Y":-2.4852,"type":"Body"},{"X":-3.7887,"Y":-3.8387,"type":"Body"},{"X":-3.0793,"Y":-2.5253,"type":"Body"},{"X":-3.0038,"Y":-3.5093,"type":"Body"},{"X":-3.5318,"Y":-3.9067,"type":"Body"},{"X":-3.6765,"Y":-3.645,"type":"Body"},{"X":-3.7725,"Y":-2.4261,"type":"Body"},{"X":-3.7868,"Y":-3.3265,"type":"Body"},{"X":-3.5115,"Y":-3.8276,"type":"Body"},{"X":-3.4641,"Y":-2.8694,"type":"Body"},{"X":-3.275,"Y":-4.3459,"type":"Body"},{"X":-3.7839,"Y":-2.4762,"type":"Body"},{"X":-3.2023,"Y":-5.3326,"type":"Wide"},{"X":-2.9313,"Y":-6.2591,"type":"Wide"},{"X":-3.8824,"Y":-7.0542,"type":"Wide"},{"X":-1.7223,"Y":-6.2075,"type":"Wide"},{"X":-2.2194,"Y":-6.267,"type":"Wide"},{"X":-3.252,"Y":-5.7646,"type":"Wide"},{"X":-1.5027,"Y":-5.374,"type":"Wide"},{"X":-2.2368,"Y":-5.3875,"type":"Wide"},{"X":-3.025,"Y":-6.2907,"type":"Wide"},{"X":-2.997,"Y":-5.7616,"type":"Wide"},{"X":-2.8266,"Y":-6.9169,"type":"Wide"},{"X":-2.9367,"Y":-6.1708,"type":"Wide"},{"X":-3.1961,"Y":-5.7519,"type":"Wide"},{"X":-3.709,"Y":-5.6382,"type":"Wide"},{"X":-3.891,"Y":-7.8169,"type":"Wide"},{"X":-2.997,"Y":-6.0838,"type":"Wide"},{"X":-2.6809,"Y":-6.7781,"type":"Wide"},{"X":-2.4739,"Y":-5.5283,"type":"Wide"},{"X":-2.8377,"Y":-6.251,"type":"Wide"},{"X":-2.6688,"Y":-6.2745,"type":"Wide"},{"X":-2.0928,"Y":-6.385,"type":"Wide"},{"X":-2.5843,"Y":-5.6086,"type":"Wide"},{"X":-2.7567,"Y":-5.6503,"type":"Wide"},{"X":-2.3155,"Y":-7.0709,"type":"Wide"},{"X":-2.7307,"Y":-5.718,"type":"Wide"},{"X":-2.2822,"Y":-5.4202,"type":"Wide"},{"X":-2.7421,"Y":-5.648,"type":"Wide"},{"X":-3.6554,"Y":-5.6524,"type":"Wide"},{"X":-2.6362,"Y":-5.9001,"type":"Wide"},{"X":-3.1179,"Y":-6.5245,"type":"Wide"},{"X":-2.8534,"Y":-6.2642,"type":"Wide"},{"X":-2.9031,"Y":-5.9845,"type":"Wide"},{"X":-3.1649,"Y":-6.8272,"type":"Wide"},{"X":-2.2896,"Y":-6.863,"type":"Wide"},{"X":-3.0143,"Y":-6.4154,"type":"Wide"},{"X":-1.9823,"Y":-5.5927,"type":"Wide"},{"X":-2.575,"Y":-6.3882,"type":"Wide"},{"X":-4.0643,"Y":-6.0432,"type":"Wide"},{"X":-2.7583,"Y":-5.3059,"type":"Wide"},{"X":-2.9874,"Y":-6.1166,"type":"Wide"},{"X":-3.0569,"Y":-6.1271,"type":"Wide"},{"X":-2.312,"Y":-6.522,"type":"Wide"},{"X":-1.3114,"Y":-5.2118,"type":"Wide"},{"X":-3.1468,"Y":-6.3823,"type":"Wide"},{"X":-4.0525,"Y":-7.6459,"type":"Wide"},{"X":-3.3903,"Y":-5.9243,"type":"Wide"},{"X":-3.2048,"Y":-6.5795,"type":"Wide"},{"X":-1.4774,"Y":-5.7471,"type":"Wide"},{"X":-2.4227,"Y":-6.5381,"type":"Wide"},{"X":-2.7999,"Y":-6.7544,"type":"Wide"},{"X":-2.6537,"Y":-7.2442,"type":"Wide"},{"X":-3.4149,"Y":-7.6522,"type":"Wide"},{"X":-3.4089,"Y":-7.3199,"type":"Wide"},{"X":-1.8801,"Y":-5.3879,"type":"Wide"},{"X":-4.1162,"Y":-7.4595,"type":"Wide"},{"X":-3.3736,"Y":-7.0085,"type":"Wide"},{"X":-3.1231,"Y":-5.7799,"type":"Wide"},{"X":-2.3814,"Y":-6.3829,"type":"Wide"},{"X":-2.4661,"Y":-5.9637,"type":"Wide"},{"X":-2.7144,"Y":-5.9424,"type":"Wide"},{"X":-2.571,"Y":-4.8312,"type":"Wide"},{"X":-1.6987,"Y":-5.6666,"type":"Wide"},{"X":-2.9274,"Y":-6.4272,"type":"Wide"},{"X":-1.7064,"Y":-5.372,"type":"Wide"},{"X":-3.669,"Y":-6.2211,"type":"Wide"},{"X":-2.7414,"Y":-6.2509,"type":"Wide"},{"X":-2.386,"Y":-6.5536,"type":"Wide"},{"X":-2.8858,"Y":-5.6658,"type":"Wide"},{"X":-4.9121,"Y":-6.8277,"type":"Wide"},{"X":-2.7538,"Y":-7.0002,"type":"Wide"},{"X":-3.0969,"Y":-6.5133,"type":"Wide"},{"X":-3.4743,"Y":-5.2592,"type":"Wide"},{"X":-3.1558,"Y":-6.2468,"type":"Wide"},{"X":-2.6863,"Y":-6.4683,"type":"Wide"},{"X":-3.3124,"Y":-7.1798,"type":"Wide"},{"X":-3.2394,"Y":-6.0679,"type":"Wide"},{"X":-2.7531,"Y":-6.8096,"type":"Wide"},{"X":-2.069,"Y":-5.5525,"type":"Wide"},{"X":-3.1325,"Y":-6.6583,"type":"Wide"},{"X":-1.799,"Y":-5.4626,"type":"Wide"},{"X":-3.6987,"Y":-5.9687,"type":"Wide"},{"X":-3.0787,"Y":-6.7084,"type":"Wide"},{"X":-2.1216,"Y":-7.2936,"type":"Wide"},{"X":-2.7494,"Y":-6.707,"type":"Wide"},{"X":-2.8689,"Y":-6.6428,"type":"Wide"},{"X":-2.1936,"Y":-6.6645,"type":"Wide"},{"X":-2.1638,"Y":-7.0986,"type":"Wide"},{"X":-2.4969,"Y":-6.6144,"type":"Wide"},{"X":-3.2883,"Y":-7.9644,"type":"Wide"},{"X":-2.6266,"Y":-7.0144,"type":"Wide"},{"X":-3.0305,"Y":-5.7325,"type":"Wide"},{"X":-3.8999,"Y":-6.1843,"type":"Wide"},{"X":-1.4304,"Y":-5.1673,"type":"Wide"},{"X":-2.424,"Y":-7.2039,"type":"Wide"},{"X":-2.8801,"Y":-6.0267,"type":"Wide"},{"X":-3.5302,"Y":-6.7266,"type":"Wide"},{"X":-2.8554,"Y":-5.0479,"type":"Wide"},{"X":0.0571,"Y":-4.1934,"type":"Wide"},{"X":-3.912,"Y":-6.7788,"type":"Wide"},{"X":-2.9894,"Y":-7.1539,"type":"Wide"},{"X":-3.7863,"Y":-7.864,"type":"Wide"},{"X":-2.2451,"Y":-5.118,"type":"Wide"},{"X":-2.3757,"Y":-5.0533,"type":"Wide"},{"X":-2.0756,"Y":-8.1571,"type":"Wide"},{"X":-4.4457,"Y":-6.5912,"type":"Wide"},{"X":-3.9067,"Y":-6.9999,"type":"Wide"},{"X":-3.417,"Y":-5.9595,"type":"Wide"},{"X":-2.5335,"Y":-6.0103,"type":"Wide"},{"X":-2.7109,"Y":-5.6604,"type":"Wide"},{"X":-3.5346,"Y":-6.4493,"type":"Wide"},{"X":-3.1368,"Y":-5.4181,"type":"Wide"},{"X":-1.9721,"Y":-5.2383,"type":"Wide"},{"X":-2.6176,"Y":-6.8197,"type":"Wide"},{"X":-3.054,"Y":-5.4128,"type":"Wide"},{"X":-3.3943,"Y":-6.0646,"type":"Wide"},{"X":-1.7366,"Y":-5.8132,"type":"Wide"},{"X":-2.9937,"Y":-6.4149,"type":"Wide"},{"X":-1.7947,"Y":-6.0331,"type":"Wide"},{"X":-3.4113,"Y":-5.3309,"type":"Wide"},{"X":-2.3545,"Y":-5.7052,"type":"Wide"},{"X":-3.2177,"Y":-6.221,"type":"Wide"},{"X":-3.8464,"Y":-7.3342,"type":"Wide"},{"X":-1.9101,"Y":-5.2848,"type":"Wide"},{"X":-2.1011,"Y":-5.5466,"type":"Wide"},{"X":-3.3192,"Y":-5.4608,"type":"Wide"},{"X":-2.5261,"Y":-6.1121,"type":"Wide"},{"X":-2.5169,"Y":-6.1742,"type":"Wide"},{"X":-3.162,"Y":-6.1166,"type":"Wide"},{"X":-3.5344,"Y":-5.8296,"type":"Wide"},{"X":-2.8718,"Y":-5.5461,"type":"Wide"},{"X":-3.8085,"Y":-6.1843,"type":"Wide"},{"X":-2.8308,"Y":-6.7149,"type":"Wide"},{"X":-1.8745,"Y":-6.7961,"type":"Wide"},{"X":-4.1456,"Y":-6.9651,"type":"Wide"},{"X":-2.8772,"Y":-5.9462,"type":"Wide"},{"X":-3.2446,"Y":-7.0149,"type":"Wide"},{"X":-2.8862,"Y":-5.7115,"type":"Wide"},{"X":-3.1443,"Y":-5.3771,"type":"Wide"},{"X":-3.2867,"Y":-6.8063,"type":"Wide"},{"X":-3.1251,"Y":-7.1398,"type":"Wide"},{"X":-1.6554,"Y":-5.3394,"type":"Wide"},{"X":-2.9461,"Y":-5.887,"type":"Wide"},{"X":-2.8458,"Y":-6.6469,"type":"Wide"},{"X":-3.5401,"Y":-6.7257,"type":"Wide"},{"X":-2.9905,"Y":-6.8364,"type":"Wide"},{"X":-3.3867,"Y":-6.2976,"type":"Wide"},{"X":-1.2312,"Y":-5.8045,"type":"Wide"},{"X":-2.3705,"Y":-5.5795,"type":"Wide"},{"X":-2.366,"Y":-5.5728,"type":"Wide"},{"X":-2.7579,"Y":-6.4317,"type":"Wide"},{"X":-3.2869,"Y":-7.0404,"type":"Wide"},{"X":-3.9636,"Y":-5.7919,"type":"Wide"},{"X":-1.9466,"Y":-6.4184,"type":"Wide"},{"X":-3.6985,"Y":-5.497,"type":"Wide"},{"X":-3.1979,"Y":-4.9578,"type":"Wide"},{"X":-3.2437,"Y":-6.8922,"type":"Wide"},{"X":-1.3319,"Y":-5.218,"type":"Wide"},{"X":-2.9171,"Y":-5.3392,"type":"Wide"},{"X":-3.7759,"Y":-7.3917,"type":"Wide"},{"X":-2.8459,"Y":-6.8336,"type":"Wide"},{"X":-3.6674,"Y":-7.4807,"type":"Wide"},{"X":-2.0905,"Y":-6.8722,"type":"Wide"},{"X":-2.6955,"Y":-6.9081,"type":"Wide"},{"X":-3.512,"Y":-5.4805,"type":"Wide"},{"X":-2.8577,"Y":-6.2929,"type":"Wide"},{"X":-2.6424,"Y":-5.2973,"type":"Wide"},{"X":-2.8625,"Y":-7.2508,"type":"Wide"},{"X":-2.482,"Y":-6.3955,"type":"Wide"},{"X":-3.7195,"Y":-6.1822,"type":"Wide"},{"X":-1.0733,"Y":-5.3265,"type":"Wide"},{"X":-1.5018,"Y":-5.566,"type":"Wide"},{"X":-3.0047,"Y":-6.8524,"type":"Wide"},{"X":-3.1055,"Y":-6.7012,"type":"Wide"},{"X":-2.7093,"Y":-5.763,"type":"Wide"},{"X":-3.2276,"Y":-5.179,"type":"Wide"},{"X":-3.2454,"Y":-5.51,"type":"Wide"},{"X":-1.5952,"Y":-6.2856,"type":"Wide"},{"X":-3.5348,"Y":-6.1067,"type":"Wide"},{"X":-3.0249,"Y":-6.533,"type":"Wide"},{"X":-2.4148,"Y":-6.933,"type":"Wide"},{"X":-2.0632,"Y":-5.4899,"type":"Wide"},{"X":-2.9734,"Y":-6.447,"type":"Wide"},{"X":-3.7718,"Y":-6.2024,"type":"Wide"},{"X":-3.9648,"Y":-6.301,"type":"Wide"},{"X":-2.8858,"Y":-6.5368,"type":"Wide"},{"X":-2.7465,"Y":-6.0672,"type":"Wide"},{"X":-2.5243,"Y":-6.2292,"type":"Wide"},{"X":-2.8928,"Y":-7.3413,"type":"Wide"},{"X":-2.7388,"Y":-6.6566,"type":"Wide"},{"X":-2.379,"Y":-5.1757,"type":"Wide"},{"X":-3.4105,"Y":-5.1086,"type":"Wide"},{"X":-2.4253,"Y":-6.6626,"type":"Wide"},{"X":-3.0034,"Y":-5.9889,"type":"Wide"},{"X":-3.2937,"Y":-7.304,"type":"Wide"},{"X":-1.3095,"Y":-4.9531,"type":"Wide"},{"X":-4.5212,"Y":-5.9758,"type":"Wide"},{"X":-2.9379,"Y":-6.5094,"type":"Wide"},{"X":-2.9954,"Y":-6.2704,"type":"Wide"},{"X":-2.081,"Y":-5.3523,"type":"Wide"},{"X":-3.0057,"Y":-6.3564,"type":"Wide"},{"X":-3.0261,"Y":-6.0563,"type":"Wide"},{"X":-2.8869,"Y":-6.1466,"type":"Wide"},{"X":-2.4533,"Y":-6.3808,"type":"Wide"},{"X":-3.0355,"Y":-5.7999,"type":"Wide"},{"X":-1.7501,"Y":-5.8074,"type":"Wide"},{"X":-3.1252,"Y":-5.955,"type":"Wide"},{"X":-2.0122,"Y":-4.685,"type":"Wide"},{"X":-3.0976,"Y":-6.0764,"type":"Wide"},{"X":-3.0103,"Y":-6.449,"type":"Wide"},{"X":-1.221,"Y":-5.8387,"type":"Wide"},{"X":-2.4424,"Y":-6.2075,"type":"Wide"},{"X":-1.6328,"Y":-5.8703,"type":"Wide"},{"X":-2.8177,"Y":-7.0288,"type":"Wide"},{"X":-2.9291,"Y":-6.1069,"type":"Wide"},{"X":-3.1783,"Y":-7.4037,"type":"Wide"},{"X":-2.6592,"Y":-6.1232,"type":"Wide"},{"X":-3.315,"Y":-6.2362,"type":"Wide"},{"X":-2.3269,"Y":-6.0905,"type":"Wide"},{"X":-3.6236,"Y":-5.9295,"type":"Wide"},{"X":-2.0954,"Y":-6.7548,"type":"Wide"},{"X":-2.4193,"Y":-5.9739,"type":"Wide"},{"X":-3.3792,"Y":-6.5056,"type":"Wide"},{"X":-3.7307,"Y":-6.0631,"type":"Wide"},{"X":-3.86,"Y":-6.0972,"type":"Wide"},{"X":-2.6264,"Y":-6.4086,"type":"Wide"},{"X":-1.0996,"Y":-5.7017,"type":"Wide"},{"X":-2.4811,"Y":-6.3796,"type":"Wide"},{"X":-3.3592,"Y":-7.645,"type":"Wide"},{"X":-3.4662,"Y":-5.0844,"type":"Wide"},{"X":-1.8547,"Y":-5.1512,"type":"Wide"},{"X":-2.6212,"Y":-6.5091,"type":"Wide"},{"X":-1.6248,"Y":-5.1832,"type":"Wide"},{"X":-3.2346,"Y":-6.8504,"type":"Wide"},{"X":-3.23,"Y":-6.6461,"type":"Wide"},{"X":-1.7302,"Y":-5.2838,"type":"Wide"},{"X":-3.0701,"Y":-5.8604,"type":"Wide"},{"X":-3.1868,"Y":-5.871,"type":"Wide"},{"X":-3.184,"Y":-5.1484,"type":"Wide"},{"X":-4.4249,"Y":-6.945,"type":"Wide"},{"X":-1.639,"Y":-4.8153,"type":"Wide"},{"X":-3.2231,"Y":-5.0628,"type":"Wide"},{"X":-2.8108,"Y":-5.8419,"type":"Wide"},{"X":-2.4189,"Y":-5.3894,"type":"Wide"},{"X":-3.2702,"Y":-5.5919,"type":"Wide"},{"X":-3.0811,"Y":-5.855,"type":"Wide"},{"X":-1.677,"Y":-5.4926,"type":"Wide"},{"X":-2.5583,"Y":-5.4583,"type":"Wide"},{"X":-3.3722,"Y":-6.0846,"type":"Wide"},{"X":-2.4211,"Y":-6.2462,"type":"Wide"},{"X":-3.4252,"Y":-7.437,"type":"Wide"},{"X":-2.5822,"Y":-6.0794,"type":"Wide"},{"X":-2.5613,"Y":-5.0107,"type":"Wide"},{"X":-2.921,"Y":-6.7911,"type":"Wide"},{"X":-3.7846,"Y":-7.4332,"type":"Wide"},{"X":-2.2997,"Y":-6.4168,"type":"Wide"},{"X":-0.9884,"Y":-5.7462,"type":"Wide"},{"X":0.5761,"Y":-3.9668,"type":"Wide"},{"X":-3.2653,"Y":-6.1316,"type":"Wide"},{"X":-1.4262,"Y":-5.2922,"type":"Wide"},{"X":-3.8254,"Y":-7.3781,"type":"Wide"},{"X":-3.3438,"Y":-6.6367,"type":"Wide"},{"X":-2.8472,"Y":-6.4558,"type":"Wide"},{"X":-2.6793,"Y":-6.4277,"type":"Wide"},{"X":-4.4988,"Y":-6.663,"type":"Wide"},{"X":-2.9437,"Y":-5.7666,"type":"Wide"},{"X":-4.8595,"Y":-7.0704,"type":"Wide"},{"X":-1.7661,"Y":-5.6046,"type":"Wide"},{"X":-1.5412,"Y":-5.8271,"type":"Wide"},{"X":-1.5898,"Y":-5.5682,"type":"Wide"},{"X":-3.1369,"Y":-6.3893,"type":"Wide"},{"X":-3.2034,"Y":-7.3368,"type":"Wide"},{"X":-3.1857,"Y":-7.7643,"type":"Wide"},{"X":-2.3608,"Y":-6.4153,"type":"Wide"},{"X":-2.8025,"Y":-5.7056,"type":"Wide"},{"X":-2.879,"Y":-5.2503,"type":"Wide"},{"X":-3.0074,"Y":-5.6689,"type":"Wide"},{"X":-1.7017,"Y":-5.523,"type":"Wide"},{"X":-2.7039,"Y":-5.84,"type":"Wide"},{"X":-2.9276,"Y":-5.3767,"type":"Wide"},{"X":-2.6381,"Y":-6.0697,"type":"Wide"},{"X":-3.2911,"Y":-6.1766,"type":"Wide"},{"X":-3.0177,"Y":-4.674,"type":"Wide"},{"X":-3.1675,"Y":-6.0769,"type":"Wide"},{"X":-2.8933,"Y":-6.4444,"type":"Wide"},{"X":-3.6519,"Y":-6.0465,"type":"Wide"},{"X":-2.8345,"Y":-6.0699,"type":"Wide"},{"X":-2.62,"Y":-5.7903,"type":"Wide"},{"X":-1.1936,"Y":-5.5157,"type":"Wide"},{"X":-2.3662,"Y":-6.5673,"type":"Wide"},{"X":-2.8276,"Y":-6.4078,"type":"Wide"},{"X":-3.9505,"Y":-6.5045,"type":"Wide"},{"X":-3.1341,"Y":-5.7884,"type":"Wide"},{"X":-3.3096,"Y":-6.2094,"type":"Wide"},{"X":-3.1798,"Y":-6.2153,"type":"Wide"},{"X":-2.354,"Y":-5.6004,"type":"Wide"},{"X":-2.7993,"Y":-5.7568,"type":"Wide"},{"X":-3.4604,"Y":-7.0697,"type":"Wide"},{"X":-2.2961,"Y":-6.9266,"type":"Wide"},{"X":-2.9138,"Y":-6.0116,"type":"Wide"},{"X":-2.9363,"Y":-5.9287,"type":"Wide"},{"X":-2.6829,"Y":-6.1477,"type":"Wide"},{"X":-3.0745,"Y":-7.4916,"type":"Wide"},{"X":-2.3029,"Y":-6.3605,"type":"Wide"},{"X":-2.7839,"Y":-6.1633,"type":"Wide"},{"X":-2.0152,"Y":-6.6581,"type":"Wide"},{"X":-3.2339,"Y":-6.579,"type":"Wide"},{"X":-2.9827,"Y":-6.8266,"type":"Wide"},{"X":3.3262,"Y":-5.1403,"type":"Wide"},{"X":-2.53,"Y":-6.1723,"type":"Wide"},{"X":-4.5792,"Y":-6.9163,"type":"Wide"},{"X":-2.0572,"Y":-5.6434,"type":"Wide"},{"X":-3.5803,"Y":-7.6212,"type":"Wide"},{"X":-2.8701,"Y":-6.1993,"type":"Wide"},{"X":-2.983,"Y":-7.4797,"type":"Wide"},{"X":-2.8563,"Y":-6.6805,"type":"Wide"},{"X":-2.2904,"Y":-5.5116,"type":"Wide"},{"X":-2.837,"Y":-6.0885,"type":"Wide"},{"X":-3.7585,"Y":-6.2398,"type":"Wide"},{"X":-1.9668,"Y":-6.7796,"type":"Wide"},{"X":-2.5611,"Y":-6.6483,"type":"Wide"},{"X":-2.2848,"Y":-5.5235,"type":"Wide"},{"X":-3.4038,"Y":-6.3382,"type":"Wide"},{"X":-2.7142,"Y":-6.5885,"type":"Wide"},{"X":-2.6914,"Y":-6.0003,"type":"Wide"},{"X":-3.646,"Y":-6.0776,"type":"Wide"},{"X":-2.0847,"Y":-6.3005,"type":"Wide"},{"X":-2.9259,"Y":-6.7764,"type":"Wide"},{"X":-2.7072,"Y":-7.0516,"type":"Wide"},{"X":-4.1065,"Y":-6.2183,"type":"Wide"},{"X":-2.3061,"Y":-6.5787,"type":"Wide"},{"X":-3.9252,"Y":-4.9249,"type":"Wide"},{"X":-1.2201,"Y":-5.3056,"type":"Wide"},{"X":-3.0762,"Y":-5.7881,"type":"Wide"},{"X":-3.5497,"Y":-8.0682,"type":"Wide"},{"X":-4.3257,"Y":-7.4078,"type":"Wide"},{"X":-3.4873,"Y":-5.3184,"type":"Wide"},{"X":-3.1876,"Y":-6.1349,"type":"Wide"},{"X":-2.0143,"Y":-5.6257,"type":"Wide"},{"X":-3.5392,"Y":-5.8963,"type":"Wide"},{"X":-3.0075,"Y":-5.8018,"type":"Wide"},{"X":-3.1471,"Y":-6.0567,"type":"Wide"},{"X":-3.0138,"Y":-6.9479,"type":"Wide"},{"X":-2.9587,"Y":-8.0373,"type":"Wide"},{"X":-3.9833,"Y":-5.6119,"type":"Wide"},{"X":-2.8264,"Y":-5.9689,"type":"Wide"},{"X":-2.8383,"Y":-5.9513,"type":"Wide"},{"X":-2.0979,"Y":-6.6817,"type":"Wide"},{"X":-2.9988,"Y":-5.7669,"type":"Wide"},{"X":-1.7213,"Y":-5.2998,"type":"Wide"},{"X":-3.9751,"Y":-6.0149,"type":"Wide"},{"X":-2.8904,"Y":-5.7673,"type":"Wide"},{"X":-2.2791,"Y":-6.3305,"type":"Wide"},{"X":-1.5176,"Y":-5.2226,"type":"Wide"},{"X":-2.1171,"Y":-6.488,"type":"Wide"},{"X":-2.7433,"Y":-6.3195,"type":"Wide"},{"X":-3.2363,"Y":-6.4717,"type":"Wide"},{"X":-3.4457,"Y":-6.7027,"type":"Wide"},{"X":-1.7126,"Y":-4.9823,"type":"Wide"},{"X":-3.0852,"Y":-5.311,"type":"Wide"},{"X":-3.52,"Y":-5.9236,"type":"Wide"},{"X":-3.7205,"Y":-5.7909,"type":"Wide"},{"X":-1.8082,"Y":-5.6051,"type":"Wide"},{"X":-3.2886,"Y":-5.2292,"type":"Wide"},{"X":-2.558,"Y":-5.752,"type":"Wide"},{"X":-3.0651,"Y":-6.3401,"type":"Wide"},{"X":-2.5847,"Y":-6.0078,"type":"Wide"},{"X":-5.5642,"Y":-4.1554,"type":"Wide"},{"X":-2.283,"Y":-5.7389,"type":"Wide"},{"X":-1.9177,"Y":-6.7011,"type":"Wide"},{"X":-3.8071,"Y":-7.5563,"type":"Wide"},{"X":-2.9965,"Y":-5.8546,"type":"Wide"},{"X":-2.8706,"Y":-6.789,"type":"Wide"},{"X":-3.033,"Y":-4.9412,"type":"Wide"},{"X":-3.2905,"Y":-6.0052,"type":"Wide"},{"X":-2.9824,"Y":-5.7272,"type":"Wide"},{"X":-3.2602,"Y":-5.7436,"type":"Wide"},{"X":-1.7086,"Y":-5.6306,"type":"Wide"},{"X":-2.1339,"Y":-5.5033,"type":"Wide"},{"X":-2.3892,"Y":-4.8576,"type":"Wide"},{"X":-3.2639,"Y":-5.8136,"type":"Wide"},{"X":-2.4215,"Y":-6.1931,"type":"Wide"},{"X":-2.9223,"Y":-6.6504,"type":"Wide"},{"X":-3.5276,"Y":-6.8417,"type":"Wide"},{"X":-1.6408,"Y":-6.5945,"type":"Wide"},{"X":-3.7761,"Y":-5.5572,"type":"Wide"},{"X":-3.1795,"Y":-7.4068,"type":"Wide"},{"X":-2.486,"Y":-6.2971,"type":"Wide"},{"X":-1.7785,"Y":-5.4441,"type":"Wide"},{"X":-3.0837,"Y":-5.8732,"type":"Wide"},{"X":-2.9823,"Y":-6.1681,"type":"Wide"},{"X":-2.4582,"Y":-6.3694,"type":"Wide"},{"X":-2.6256,"Y":-5.208,"type":"Wide"},{"X":-3.1561,"Y":-6.1188,"type":"Wide"},{"X":-3.7975,"Y":-7.3938,"type":"Wide"},{"X":-1.9386,"Y":-5.249,"type":"Wide"},{"X":-2.7524,"Y":-6.9485,"type":"Wide"},{"X":-1.705,"Y":-5.5642,"type":"Wide"},{"X":-2.2847,"Y":-6.0389,"type":"Wide"},{"X":-2.8312,"Y":-6.3873,"type":"Wide"},{"X":-1.7071,"Y":-5.2335,"type":"Wide"},{"X":-2.0163,"Y":-5.3513,"type":"Wide"},{"X":-3.2934,"Y":-6.2113,"type":"Wide"},{"X":-2.8849,"Y":-6.4622,"type":"Wide"},{"X":-2.5397,"Y":-6.5974,"type":"Wide"},{"X":-2.7938,"Y":-6.0523,"type":"Wide"},{"X":-3.2575,"Y":-6.1529,"type":"Wide"},{"X":-4.0241,"Y":-5.5273,"type":"Wide"},{"X":-2.0273,"Y":-5.2664,"type":"Wide"},{"X":-2.8231,"Y":-5.8428,"type":"Wide"},{"X":-2.9483,"Y":-5.8109,"type":"Wide"},{"X":-2.7014,"Y":-6.7334,"type":"Wide"},{"X":-3.4034,"Y":-5.968,"type":"Wide"},{"X":-2.6128,"Y":-6.2165,"type":"Wide"},{"X":-1.4873,"Y":-6.0532,"type":"Wide"},{"X":-2.2621,"Y":-6.5563,"type":"Wide"},{"X":-3.4663,"Y":-5.9585,"type":"Wide"},{"X":-2.4876,"Y":-5.9123,"type":"Wide"},{"X":-3.015,"Y":-6.0114,"type":"Wide"},{"X":-3.1132,"Y":-6.576,"type":"Wide"},{"X":-2.587,"Y":-7.1051,"type":"Wide"},{"X":-1.9954,"Y":-5.6447,"type":"Wide"},{"X":-1.1767,"Y":-5.4829,"type":"Wide"},{"X":-3.1194,"Y":-6.7093,"type":"Wide"},{"X":-1.5552,"Y":-5.0374,"type":"Wide"},{"X":-2.9698,"Y":-5.4334,"type":"Wide"},{"X":-1.6269,"Y":-5.5229,"type":"Wide"},{"X":-2.9538,"Y":-6.9053,"type":"Wide"},{"X":-3.1115,"Y":-5.5525,"type":"Wide"},{"X":-3.0845,"Y":-6.0773,"type":"Wide"},{"X":-3.3859,"Y":-5.9744,"type":"Wide"},{"X":-2.4427,"Y":-5.9641,"type":"Wide"},{"X":-3.7345,"Y":-5.9885,"type":"Wide"},{"X":-2.7883,"Y":-5.6451,"type":"Wide"},{"X":-2.1212,"Y":-7.551,"type":"Wide"},{"X":-2.6941,"Y":-6.7323,"type":"Wide"},{"X":-2.7709,"Y":-6.8159,"type":"Wide"},{"X":-2.973,"Y":-5.9433,"type":"Wide"},{"X":-2.7948,"Y":-5.6305,"type":"Wide"},{"X":-2.5555,"Y":-6.6782,"type":"Wide"},{"X":-3.3693,"Y":-6.0934,"type":"Wide"},{"X":-3.6735,"Y":-7.7084,"type":"Wide"},{"X":-1.9819,"Y":-7.3859,"type":"Wide"},{"X":-1.8279,"Y":-6.4292,"type":"Wide"},{"X":-3.4127,"Y":-7.3069,"type":"Wide"},{"X":-3.3933,"Y":-5.751,"type":"Wide"},{"X":-2.5567,"Y":-6.0415,"type":"Wide"},{"X":-2.6264,"Y":-7.226,"type":"Wide"},{"X":-2.4391,"Y":-6.8291,"type":"Wide"},{"X":-2.8115,"Y":-7.1096,"type":"Wide"},{"X":-3.4552,"Y":-5.2708,"type":"Wide"},{"X":-2.4367,"Y":-6.0783,"type":"Wide"},{"X":-2.8425,"Y":-6.7506,"type":"Wide"},{"X":-3.0674,"Y":-5.6141,"type":"Wide"},{"X":-3.3173,"Y":-6.2058,"type":"Wide"},{"X":-2.2449,"Y":-6.9481,"type":"Wide"},{"X":-3.2791,"Y":-6.5321,"type":"Wide"},{"X":-1.4465,"Y":-4.8046,"type":"Wide"},{"X":-2.6971,"Y":-6.4892,"type":"Wide"},{"X":-2.7813,"Y":-7.5503,"type":"Wide"},{"X":-2.6029,"Y":-7.6802,"type":"Wide"},{"X":-2.6523,"Y":-5.786,"type":"Wide"},{"X":-2.8113,"Y":-6.0359,"type":"Wide"},{"X":-1.3775,"Y":-6.468,"type":"Wide"},{"X":-2.6295,"Y":-4.6562,"type":"Wide"},{"X":-2.4981,"Y":-7.0727,"type":"Wide"},{"X":-2.7738,"Y":-5.1509,"type":"Wide"},{"X":-2.9669,"Y":-6.4146,"type":"Wide"},{"X":-2.356,"Y":-4.6707,"type":"Wide"},{"X":-1.7961,"Y":-5.2795,"type":"Wide"},{"X":-2.2438,"Y":-7.6899,"type":"Wide"},{"X":-3.14,"Y":-6.9832,"type":"Wide"},{"X":-1.5065,"Y":-4.8832,"type":"Wide"},{"X":-2.875,"Y":-5.8011,"type":"Wide"},{"X":-3.0918,"Y":-5.8108,"type":"Wide"},{"X":-2.4219,"Y":-6.6587,"type":"Wide"},{"X":-2.9194,"Y":-6.1995,"type":"Wide"},{"X":-3.3706,"Y":-6.0949,"type":"Wide"},{"X":-2.7427,"Y":-6.8015,"type":"Wide"},{"X":-2.6836,"Y":-6.3075,"type":"Wide"},{"X":-3.7829,"Y":-6.4188,"type":"Wide"},{"X":-1.7283,"Y":-5.624,"type":"Wide"},{"X":-3.5849,"Y":-5.9112,"type":"Wide"},{"X":-3.1037,"Y":-6.8681,"type":"Wide"},{"X":-3.1692,"Y":-7.0533,"type":"Wide"},{"X":-2.913,"Y":-6.4315,"type":"Wide"},{"X":-3.558,"Y":-5.9686,"type":"Wide"},{"X":-2.5084,"Y":-6.5602,"type":"Wide"},{"X":-2.7293,"Y":-6.3526,"type":"Wide"},{"X":-0.4943,"Y":-4.4185,"type":"Wide"},{"X":-3.8107,"Y":-7.0497,"type":"Wide"},{"X":-2.2801,"Y":-4.7238,"type":"Wide"},{"X":-2.4968,"Y":-6.7149,"type":"Wide"},{"X":-2.6564,"Y":-6.1776,"type":"Wide"},{"X":-3.0831,"Y":-7.5765,"type":"Wide"},{"X":-2.8498,"Y":-6.4401,"type":"Wide"},{"X":-3.5157,"Y":-5.0284,"type":"Wide"},{"X":-3.0196,"Y":-5.5167,"type":"Wide"},{"X":-2.8857,"Y":-7.0273,"type":"Wide"},{"X":-3.2784,"Y":-6.0653,"type":"Wide"},{"X":-1.9286,"Y":-6.5542,"type":"Wide"},{"X":-3.2486,"Y":-7.028,"type":"Wide"},{"X":-2.9976,"Y":-6.175,"type":"Wide"},{"X":-2.933,"Y":-6.7419,"type":"Wide"},{"X":-3.5562,"Y":-5.3251,"type":"Wide"},{"X":-3.4091,"Y":-7.1612,"type":"Wide"},{"X":-3.0994,"Y":-5.6811,"type":"Wide"},{"X":-3.2894,"Y":-7.3858,"type":"Wide"},{"X":-1.8778,"Y":-5.6698,"type":"Wide"},{"X":-3.4131,"Y":-6.6634,"type":"Wide"},{"X":-3.0888,"Y":-6.0984,"type":"Wide"},{"X":-2.7744,"Y":-6.319,"type":"Wide"},{"X":2.0383,"Y":-4.359,"type":"Wide"},{"X":-3.9108,"Y":-6.2814,"type":"Wide"},{"X":-2.7938,"Y":-6.5062,"type":"Wide"},{"X":-1.6075,"Y":-5.0254,"type":"Wide"},{"X":-3.287,"Y":-6.034,"type":"Wide"},{"X":-2.7976,"Y":-6.0932,"type":"Wide"},{"X":-3.2602,"Y":-5.8086,"type":"Wide"},{"X":-3.5419,"Y":-5.87,"type":"Wide"},{"X":-2.3757,"Y":-8.793,"type":"Wide"},{"X":-2.781,"Y":-7.0236,"type":"Wide"},{"X":-3.5394,"Y":-7.6831,"type":"Wide"},{"X":-3.3004,"Y":-6.0147,"type":"Wide"},{"X":-3.1774,"Y":-6.5854,"type":"Wide"},{"X":-2.8511,"Y":-6.0126,"type":"Wide"},{"X":-1.0355,"Y":-6.6813,"type":"Wide"},{"X":-2.1073,"Y":-5.1731,"type":"Wide"},{"X":-2.5636,"Y":-6.354,"type":"Wide"},{"X":-3.0551,"Y":-5.5558,"type":"Wide"},{"X":-1.9965,"Y":-5.7131,"type":"Wide"},{"X":-2.5829,"Y":-6.0769,"type":"Wide"},{"X":-3.4098,"Y":-6.2208,"type":"Wide"},{"X":-2.4018,"Y":-6.6143,"type":"Wide"},{"X":-1.9857,"Y":-5.4687,"type":"Wide"},{"X":-2.5056,"Y":-3.872,"type":"Wide"},{"X":-1.7652,"Y":-5.7484,"type":"Wide"},{"X":-3.2053,"Y":-5.8701,"type":"Wide"},{"X":-1.9024,"Y":-7.1672,"type":"Wide"},{"X":-3.0243,"Y":-6.0841,"type":"Wide"},{"X":-2.0806,"Y":-5.792,"type":"Wide"},{"X":-2.1029,"Y":-5.6209,"type":"Wide"},{"X":-3.0077,"Y":-6.0887,"type":"Wide"},{"X":-2.8395,"Y":-7.0661,"type":"Wide"},{"X":-1.6915,"Y":-5.394,"type":"Wide"},{"X":-1.4918,"Y":-4.7734,"type":"Wide"},{"X":-3.5638,"Y":-5.0001,"type":"Wide"},{"X":-2.6388,"Y":-5.5791,"type":"Wide"},{"X":-3.2792,"Y":-6.5295,"type":"Wide"},{"X":-2.8546,"Y":-6.3887,"type":"Wide"},{"X":-3.0846,"Y":-5.664,"type":"Wide"},{"X":-3.0266,"Y":-6.904,"type":"Wide"},{"X":-1.6445,"Y":-5.5339,"type":"Wide"},{"X":-2.7767,"Y":-5.8491,"type":"Wide"},{"X":-2.6383,"Y":-6.5219,"type":"Wide"},{"X":-3.5676,"Y":-6.0931,"type":"Wide"},{"X":-4.0403,"Y":-7.3007,"type":"Wide"},{"X":-3.4376,"Y":-6.8329,"type":"Wide"},{"X":-3.1686,"Y":-6.4903,"type":"Wide"},{"X":-3.6197,"Y":-7.1445,"type":"Wide"},{"X":-2.7154,"Y":-6.6557,"type":"Wide"},{"X":-4.0809,"Y":-5.6447,"type":"Wide"},{"X":-2.8613,"Y":-6.346,"type":"Wide"},{"X":-1.9783,"Y":-5.5985,"type":"Wide"},{"X":-2.6828,"Y":-6.0692,"type":"Wide"},{"X":-2.5688,"Y":-5.6958,"type":"Wide"},{"X":-2.8554,"Y":-6.5288,"type":"Wide"},{"X":-2.9302,"Y":-6.2117,"type":"Wide"},{"X":-2.9323,"Y":-6.7887,"type":"Wide"},{"X":-1.2789,"Y":-5.5091,"type":"Wide"},{"X":-2.4161,"Y":-6.5254,"type":"Wide"},{"X":-3.1313,"Y":-6.2689,"type":"Wide"},{"X":-1.9516,"Y":-5.7894,"type":"Wide"},{"X":-3.0186,"Y":-5.9332,"type":"Wide"},{"X":-3.3517,"Y":-6.1441,"type":"Wide"},{"X":-2.577,"Y":-6.9253,"type":"Wide"},{"X":-3.1398,"Y":-6.5042,"type":"Wide"},{"X":-3.0902,"Y":-6.3779,"type":"Wide"},{"X":-2.6585,"Y":-5.4485,"type":"Wide"},{"X":-1.8047,"Y":-5.5369,"type":"Wide"},{"X":-2.3063,"Y":-5.6284,"type":"Wide"},{"X":-2.3247,"Y":-5.9112,"type":"Wide"},{"X":-2.2991,"Y":-5.7951,"type":"Wide"},{"X":-4.2346,"Y":-5.3791,"type":"Wide"},{"X":-2.4219,"Y":-7.075,"type":"Wide"},{"X":-2.949,"Y":-6.1041,"type":"Wide"},{"X":-3.2813,"Y":-7.2671,"type":"Wide"},{"X":-2.8058,"Y":-5.6422,"type":"Wide"},{"X":-3.063,"Y":-7.1698,"type":"Wide"},{"X":-3.4253,"Y":-6.0923,"type":"Wide"},{"X":-3.7624,"Y":-6.2688,"type":"Wide"},{"X":-2.6119,"Y":-7.1018,"type":"Wide"},{"X":-3.4181,"Y":-5.294,"type":"Wide"},{"X":-1.6642,"Y":-5.2885,"type":"Wide"},{"X":-1.9471,"Y":-4.6392,"type":"Wide"},{"X":-5.7798,"Y":-6.8824,"type":"Wide"},{"X":-3.3393,"Y":-5.9251,"type":"Wide"},{"X":-2.9869,"Y":-6.0228,"type":"Wide"},{"X":-2.9928,"Y":-5.7404,"type":"Wide"},{"X":-2.6625,"Y":-6.5439,"type":"Wide"},{"X":-1.9428,"Y":-5.008,"type":"Wide"},{"X":-3.3283,"Y":-6.872,"type":"Wide"},{"X":-3.0388,"Y":-6.2364,"type":"Wide"},{"X":-2.8848,"Y":-6.3402,"type":"Wide"},{"X":-2.8385,"Y":-6.9415,"type":"Wide"},{"X":-4.3719,"Y":-6.7104,"type":"Wide"},{"X":-1.3766,"Y":-5.3619,"type":"Wide"},{"X":-2.5851,"Y":-6.4251,"type":"Wide"},{"X":-1.4289,"Y":-5.9738,"type":"Wide"},{"X":-1.5835,"Y":-6.1584,"type":"Wide"},{"X":-3.0381,"Y":-6.3338,"type":"Wide"},{"X":-1.6119,"Y":-4.7897,"type":"Wide"},{"X":-3.1162,"Y":-7.1399,"type":"Wide"},{"X":-2.7407,"Y":-6.5391,"type":"Wide"},{"X":-2.1656,"Y":-6.6432,"type":"Wide"},{"X":-2.948,"Y":-5.9002,"type":"Wide"},{"X":-2.7573,"Y":-6.4684,"type":"Wide"},{"X":-2.9087,"Y":-5.9148,"type":"Wide"},{"X":-2.9295,"Y":-6.4259,"type":"Wide"},{"X":-2.9295,"Y":-5.4275,"type":"Wide"},{"X":-1.9016,"Y":-4.661,"type":"Wide"},{"X":-2.9505,"Y":-6.0917,"type":"Wide"},{"X":-1.937,"Y":-5.7047,"type":"Wide"},{"X":-3.8605,"Y":-7.9352,"type":"Wide"},{"X":-2.8692,"Y":-6.5736,"type":"Wide"},{"X":-2.7546,"Y":-6.3135,"type":"Wide"},{"X":-2.5925,"Y":-6.8851,"type":"Wide"},{"X":-2.9433,"Y":-6.7538,"type":"Wide"},{"X":-2.3414,"Y":-4.9086,"type":"Wide"},{"X":-2.0948,"Y":-5.0271,"type":"Wide"},{"X":-2.3447,"Y":-4.8688,"type":"Wide"},{"X":-3.9582,"Y":-7.086,"type":"Wide"},{"X":-3.0929,"Y":-5.7139,"type":"Wide"},{"X":-2.873,"Y":-5.9103,"type":"Wide"},{"X":-2.978,"Y":-6.276,"type":"Wide"},{"X":-2.0399,"Y":-5.4552,"type":"Wide"},{"X":-2.6119,"Y":-6.3267,"type":"Wide"},{"X":-2.81,"Y":-5.9264,"type":"Wide"},{"X":-2.9378,"Y":-6.2413,"type":"Wide"},{"X":-3.0047,"Y":-6.5009,"type":"Wide"},{"X":-3.0818,"Y":-6.2617,"type":"Wide"},{"X":-2.214,"Y":-5.1447,"type":"Wide"},{"X":-3.0579,"Y":-6.3445,"type":"Wide"},{"X":-2.4723,"Y":-5.9788,"type":"Wide"},{"X":-3.1006,"Y":-6.6554,"type":"Wide"},{"X":-2.3256,"Y":-4.8161,"type":"Wide"},{"X":-1.7545,"Y":-5.5919,"type":"Wide"},{"X":-2.8124,"Y":-6.0613,"type":"Wide"},{"X":-2.7826,"Y":-5.9637,"type":"Wide"},{"X":-2.1958,"Y":-6.2824,"type":"Wide"},{"X":-3.1571,"Y":-5.3249,"type":"Wide"},{"X":-3.3805,"Y":-6.5373,"type":"Wide"},{"X":-2.3228,"Y":-7.7248,"type":"Wide"},{"X":-3.5211,"Y":-6.6717,"type":"Wide"},{"X":-2.5461,"Y":-5.3208,"type":"Wide"},{"X":-3.0537,"Y":-6.9956,"type":"Wide"},{"X":-2.9242,"Y":-7.2765,"type":"Wide"},{"X":-3.756,"Y":-6.2336,"type":"Wide"},{"X":-2.8468,"Y":-6.8331,"type":"Wide"},{"X":-2.0524,"Y":-5.1944,"type":"Wide"},{"X":-2.4351,"Y":-5.0514,"type":"Wide"},{"X":-2.6034,"Y":-5.8633,"type":"Wide"},{"X":-4.1996,"Y":-5.1104,"type":"Wide"},{"X":-3.2406,"Y":-5.8027,"type":"Wide"},{"X":-2.6918,"Y":-6.9327,"type":"Wide"},{"X":-2.5245,"Y":-6.741,"type":"Wide"},{"X":-3.1019,"Y":-5.4668,"type":"Wide"},{"X":-2.8904,"Y":-6.5192,"type":"Wide"},{"X":-1.8109,"Y":-5.3454,"type":"Wide"},{"X":-3.2539,"Y":-6.1732,"type":"Wide"},{"X":-3.5349,"Y":-6.958,"type":"Wide"},{"X":-3.2052,"Y":-6.1437,"type":"Wide"},{"X":-3.13,"Y":-6.0318,"type":"Wide"},{"X":-3.1593,"Y":-5.8107,"type":"Wide"},{"X":-2.5524,"Y":-5.8895,"type":"Wide"},{"X":-3.521,"Y":-7.6305,"type":"Wide"},{"X":-2.1435,"Y":-7.9833,"type":"Wide"},{"X":-2.6716,"Y":-6.7247,"type":"Wide"},{"X":-1.8055,"Y":-4.5906,"type":"Wide"},{"X":-2.6334,"Y":-6.0267,"type":"Wide"},{"X":-3.035,"Y":-6.7094,"type":"Wide"},{"X":-3.4342,"Y":-5.9987,"type":"Wide"},{"X":-1.6093,"Y":-5.3213,"type":"Wide"},{"X":-1.7741,"Y":-5.2012,"type":"Wide"},{"X":-3.4617,"Y":-7.0745,"type":"Wide"},{"X":-3.5598,"Y":-7.1068,"type":"Wide"},{"X":-3.6788,"Y":-6.7436,"type":"Wide"},{"X":-3.0494,"Y":-5.9266,"type":"Wide"},{"X":-2.8981,"Y":-5.4296,"type":"Wide"},{"X":-2.8423,"Y":-6.3945,"type":"Wide"},{"X":-3.6094,"Y":-6.596,"type":"Wide"},{"X":-3.6178,"Y":-6.1044,"type":"Wide"},{"X":-3.1335,"Y":-7.0064,"type":"Wide"},{"X":-3.7976,"Y":-4.8584,"type":"Wide"},{"X":-3.0061,"Y":-6.8122,"type":"Wide"},{"X":-2.6509,"Y":-5.5555,"type":"Wide"},{"X":-2.5337,"Y":-6.5742,"type":"Wide"},{"X":-3.2494,"Y":-6.3067,"type":"Wide"},{"X":-3.3897,"Y":-5.9915,"type":"Wide"},{"X":-1.5763,"Y":-5.7399,"type":"Wide"},{"X":-3.0064,"Y":-5.9174,"type":"Wide"},{"X":-1.9196,"Y":-5.5695,"type":"Wide"},{"X":-3.1367,"Y":-6.6315,"type":"Wide"},{"X":-3.2835,"Y":-7.0028,"type":"Wide"},{"X":-2.9933,"Y":-6.895,"type":"Wide"},{"X":-5.1113,"Y":-7.3222,"type":"Wide"},{"X":-2.6563,"Y":-6.2694,"type":"Wide"},{"X":-2.6822,"Y":-6.3106,"type":"Wide"},{"X":-3.0119,"Y":-5.5808,"type":"Wide"},{"X":-1.8883,"Y":-5.4372,"type":"Wide"},{"X":-3.1385,"Y":-7.1076,"type":"Wide"},{"X":-2.5091,"Y":-6.7299,"type":"Wide"},{"X":-1.6607,"Y":-5.5168,"type":"Wide"},{"X":-3.1619,"Y":-6.3607,"type":"Wide"},{"X":-2.4828,"Y":-7.7963,"type":"Wide"},{"X":-3.0692,"Y":-5.53,"type":"Wide"},{"X":-2.6462,"Y":-6.5306,"type":"Wide"},{"X":-2.1583,"Y":-6.4152,"type":"Wide"},{"X":-2.7212,"Y":-6.4757,"type":"Wide"},{"X":-3.7469,"Y":-6.1613,"type":"Wide"},{"X":-4.6116,"Y":-7.3429,"type":"Wide"},{"X":-3.4921,"Y":-6.7574,"type":"Wide"},{"X":-3.7178,"Y":-5.623,"type":"Wide"},{"X":-3.1942,"Y":-6.382,"type":"Wide"},{"X":-2.4129,"Y":-6.3455,"type":"Wide"},{"X":-3.1922,"Y":-7.1036,"type":"Wide"},{"X":-2.9062,"Y":-5.9367,"type":"Wide"},{"X":-3.0442,"Y":-5.6106,"type":"Wide"},{"X":-3.0714,"Y":-6.4352,"type":"Wide"},{"X":2.5685,"Y":-4.1447,"type":"Wide"},{"X":-4.4265,"Y":-7.1756,"type":"Wide"},{"X":-3.115,"Y":-6.7228,"type":"Wide"},{"X":-2.756,"Y":-6.2625,"type":"Wide"},{"X":-2.5545,"Y":-6.6048,"type":"Wide"},{"X":-2.2007,"Y":-5.2662,"type":"Wide"},{"X":-1.9574,"Y":-5.0405,"type":"Wide"},{"X":-3.3908,"Y":-6.1625,"type":"Wide"},{"X":-2.8685,"Y":-7.2363,"type":"Wide"},{"X":-2.9645,"Y":-5.5497,"type":"Wide"},{"X":-3.7695,"Y":-5.0011,"type":"Wide"},{"X":-2.3707,"Y":-6.4105,"type":"Wide"},{"X":-3.1688,"Y":-6.4848,"type":"Wide"},{"X":-3.1173,"Y":-5.7672,"type":"Wide"},{"X":-3.5859,"Y":-6.9542,"type":"Wide"},{"X":-3.3072,"Y":-5.9586,"type":"Wide"},{"X":-2.713,"Y":-6.2122,"type":"Wide"},{"X":-1.4421,"Y":-4.9709,"type":"Wide"},{"X":-4.9275,"Y":-7.0798,"type":"Wide"},{"X":-3.4621,"Y":-5.6101,"type":"Wide"},{"X":-2.3629,"Y":-6.7574,"type":"Wide"},{"X":-3.0326,"Y":-5.8976,"type":"Wide"},{"X":-2.6165,"Y":-6.4539,"type":"Wide"},{"X":0.7058,"Y":-4.6088,"type":"Wide"},{"X":-2.1024,"Y":-5.2067,"type":"Wide"},{"X":-3.4029,"Y":-7.0139,"type":"Wide"},{"X":-2.9365,"Y":-5.3636,"type":"Wide"},{"X":-2.0327,"Y":-5.6088,"type":"Wide"},{"X":-2.4016,"Y":-5.5683,"type":"Wide"},{"X":-3.0188,"Y":-6.5633,"type":"Wide"},{"X":-2.3177,"Y":-5.8533,"type":"Wide"},{"X":-2.3665,"Y":-7.6735,"type":"Wide"},{"X":-3.2386,"Y":-5.7715,"type":"Wide"},{"X":-3.4676,"Y":-6.2933,"type":"Wide"},{"X":-1.294,"Y":-5.2229,"type":"Wide"},{"X":-2.9045,"Y":-6.9214,"type":"Wide"},{"X":-2.7952,"Y":-5.7958,"type":"Wide"},{"X":-2.9156,"Y":-7.5199,"type":"Wide"},{"X":-2.646,"Y":-5.7466,"type":"Wide"},{"X":-2.4945,"Y":-6.2216,"type":"Wide"},{"X":-2.8738,"Y":-6.9186,"type":"Wide"},{"X":-3.3578,"Y":-7.0081,"type":"Wide"},{"X":-1.5682,"Y":-5.3654,"type":"Wide"},{"X":-2.5362,"Y":-6.2532,"type":"Wide"},{"X":-2.7365,"Y":-6.8805,"type":"Wide"},{"X":-3.1109,"Y":-6.7288,"type":"Wide"},{"X":-2.8739,"Y":-6.49,"type":"Wide"},{"X":-2.6461,"Y":-6.2263,"type":"Wide"},{"X":-3.0998,"Y":-6.9849,"type":"Wide"},{"X":-3.1631,"Y":-6.4133,"type":"Wide"},{"X":-3.3463,"Y":-7.6175,"type":"Wide"},{"X":-3.0241,"Y":-6.2742,"type":"Wide"},{"X":-3.1198,"Y":-5.7717,"type":"Wide"},{"X":-3.2871,"Y":-7.2729,"type":"Wide"},{"X":-2.9017,"Y":-7.2183,"type":"Wide"},{"X":-1.2343,"Y":-5.2538,"type":"Wide"},{"X":-3.6997,"Y":-6.2458,"type":"Wide"},{"X":-3.0689,"Y":-5.5644,"type":"Wide"},{"X":-3.6133,"Y":-6.0659,"type":"Wide"},{"X":-3.1639,"Y":-6.3382,"type":"Wide"},{"X":-2.6675,"Y":-4.5573,"type":"Wide"},{"X":-3.1188,"Y":-6.6521,"type":"Wide"},{"X":-3.1341,"Y":-6.5584,"type":"Wide"},{"X":-1.855,"Y":-5.1955,"type":"Wide"},{"X":-3.2144,"Y":-6.3316,"type":"Wide"},{"X":-2.8587,"Y":-6.554,"type":"Wide"},{"X":-2.2809,"Y":-6.6481,"type":"Wide"},{"X":-1.302,"Y":-5.3521,"type":"Wide"},{"X":-3.309,"Y":-6.8431,"type":"Wide"},{"X":-2.1803,"Y":-5.501,"type":"Wide"},{"X":-2.317,"Y":-6.5052,"type":"Wide"},{"X":-1.1714,"Y":-5.0868,"type":"Wide"},{"X":-4.2098,"Y":-6.9809,"type":"Wide"},{"X":-3.1236,"Y":-5.7689,"type":"Wide"},{"X":-2.566,"Y":-6.6411,"type":"Wide"},{"X":-2.9746,"Y":-5.8603,"type":"Wide"},{"X":-1.9052,"Y":-5.1755,"type":"Wide"},{"X":-3.4272,"Y":-5.8624,"type":"Wide"},{"X":-2.7065,"Y":-6.345,"type":"Wide"},{"X":-2.8263,"Y":-7.2523,"type":"Wide"},{"X":-2.1021,"Y":-6.3176,"type":"Wide"},{"X":-3.1748,"Y":-5.9056,"type":"Wide"},{"X":-2.9981,"Y":-5.2604,"type":"Wide"},{"X":-2.9709,"Y":-6.8263,"type":"Wide"},{"X":-2.6839,"Y":-5.8155,"type":"Wide"},{"X":-2.751,"Y":-5.7946,"type":"Wide"},{"X":-3.2944,"Y":-6.8608,"type":"Wide"},{"X":-1.0932,"Y":-4.6328,"type":"Wide"},{"X":-3.1131,"Y":-7.1177,"type":"Wide"},{"X":-2.4173,"Y":-6.4672,"type":"Wide"},{"X":-3.169,"Y":-5.9985,"type":"Wide"},{"X":-3.1013,"Y":-6.0851,"type":"Wide"},{"X":-1.8272,"Y":-6.4234,"type":"Wide"},{"X":-3.0096,"Y":-5.4632,"type":"Wide"},{"X":-2.8928,"Y":-6.8006,"type":"Wide"},{"X":-1.919,"Y":-5.6227,"type":"Wide"},{"X":-2.9252,"Y":-3.9672,"type":"Wide"},{"X":-2.5304,"Y":-4.9671,"type":"Wide"},{"X":-2.1227,"Y":-4.8777,"type":"Wide"},{"X":-3.4674,"Y":-6.538,"type":"Wide"},{"X":-2.923,"Y":-6.2703,"type":"Wide"},{"X":-2.9017,"Y":-6.5389,"type":"Wide"},{"X":-2.8109,"Y":-6.4811,"type":"Wide"},{"X":-2.4248,"Y":-7.2561,"type":"Wide"},{"X":-2.1307,"Y":-4.9139,"type":"Wide"},{"X":-2.8821,"Y":-5.9583,"type":"Wide"},{"X":-2.1894,"Y":-6.3244,"type":"Wide"},{"X":-3.7975,"Y":-6.4638,"type":"Wide"},{"X":-3.2842,"Y":-6.0602,"type":"Wide"},{"X":-2.915,"Y":-5.7134,"type":"Wide"},{"X":-3.1274,"Y":-7.305,"type":"Wide"},{"X":-3.3514,"Y":-6.7356,"type":"Wide"},{"X":-1.9612,"Y":-4.8581,"type":"Wide"},{"X":-3.0733,"Y":-5.9926,"type":"Wide"},{"X":-2.318,"Y":-4.8031,"type":"Wide"},{"X":-2.045,"Y":-7.2749,"type":"Wide"},{"X":-2.5708,"Y":-6.4498,"type":"Wide"},{"X":-3.446,"Y":-5.6051,"type":"Wide"},{"X":-2.307,"Y":-7.1347,"type":"Wide"},{"X":-3.0497,"Y":-6.653,"type":"Wide"},{"X":-2.2334,"Y":-5.2796,"type":"Wide"},{"X":-3.0753,"Y":-5.0301,"type":"Wide"},{"X":-3.1213,"Y":-5.9347,"type":"Wide"},{"X":-1.6819,"Y":-5.5811,"type":"Wide"},{"X":-3.1938,"Y":-7.0129,"type":"Wide"},{"X":-3.5749,"Y":-7.5972,"type":"Wide"},{"X":-3.7001,"Y":-7.0525,"type":"Wide"},{"X":-2.3164,"Y":-5.9048,"type":"Wide"},{"X":-1.1333,"Y":-5.268,"type":"Wide"},{"X":-2.9667,"Y":-5.112,"type":"Wide"},{"X":-3.4425,"Y":-6.9565,"type":"Wide"},{"X":-3.4562,"Y":-6.6695,"type":"Wide"},{"X":-2.3113,"Y":-5.0644,"type":"Wide"},{"X":-2.8129,"Y":-5.4005,"type":"Wide"},{"X":-1.8192,"Y":-5.6029,"type":"Wide"},{"X":-3.3332,"Y":-6.4762,"type":"Wide"},{"X":-3.2166,"Y":-6.3874,"type":"Wide"},{"X":-3.8325,"Y":-6.681,"type":"Wide"},{"X":-3.1149,"Y":-7.013,"type":"Wide"},{"X":-1.7483,"Y":-6.4043,"type":"Wide"},{"X":-3.2206,"Y":-6.4411,"type":"Wide"},{"X":-3.097,"Y":-6.5392,"type":"Wide"},{"X":-3.1199,"Y":-6.5196,"type":"Wide"},{"X":-1.775,"Y":-5.1339,"type":"Wide"},{"X":-2.9134,"Y":-6.3829,"type":"Wide"},{"X":-3.6536,"Y":-5.8775,"type":"Wide"},{"X":-2.8309,"Y":-6.2849,"type":"Wide"},{"X":-1.4082,"Y":-5.5963,"type":"Wide"},{"X":-2.8857,"Y":-6.1841,"type":"Wide"},{"X":-2.82,"Y":-6.0987,"type":"Wide"},{"X":-3.4152,"Y":-7.4157,"type":"Wide"},{"X":-1.5455,"Y":-6.2835,"type":"Wide"},{"X":-3.2747,"Y":-5.9944,"type":"Wide"},{"X":-2.3092,"Y":-5.5361,"type":"Wide"},{"X":-1.6634,"Y":-4.7943,"type":"Wide"},{"X":-2.4161,"Y":-5.953,"type":"Wide"},{"X":-3.0978,"Y":-5.7344,"type":"Wide"},{"X":-2.5812,"Y":-5.9422,"type":"Wide"},{"X":-3.0682,"Y":-6.984,"type":"Wide"},{"X":-3.2544,"Y":-6.6469,"type":"Wide"},{"X":-3.2676,"Y":-5.95,"type":"Wide"},{"X":-2.7447,"Y":-6.9647,"type":"Wide"},{"X":-3.2455,"Y":-6.6389,"type":"Wide"},{"X":-2.9309,"Y":-6.7685,"type":"Wide"},{"X":-2.8593,"Y":-7.1513,"type":"Wide"},{"X":2.6631,"Y":-4.214,"type":"Wide"},{"X":-2.9912,"Y":-5.6423,"type":"Wide"},{"X":-3.5014,"Y":-6.3984,"type":"Wide"},{"X":-2.7337,"Y":-5.6941,"type":"Wide"},{"X":-2.9511,"Y":-6.2223,"type":"Wide"},{"X":-3.4425,"Y":-5.5404,"type":"Wide"},{"X":-3.2976,"Y":-6.8434,"type":"Wide"}]
